src/Testing/HPC3/Share_1/hpc3.v
module HPC3(
    clk,
    a0,
    a1,
    b0,
    b1,
    r01,
    p01,
    c0,
    c1
);
//INPUTS
    input clk;
    input  [7:0] a0;
    input  [7:0] a1;
    input  [7:0] b0;
    input  [7:0] b1;
    input  [7:0] r01;
    input  [7:0] p01;
//OUTPUTS
    output reg  [7:0] c0;
    output reg  [7:0] c1;
//Intermediate values
    wire [7:0] a0_inp;
    wire [7:0] a1_inp;
    wire [7:0] b0_inp;
    wire [7:0] b1_inp;
    wire [7:0] r01_inp;
    wire [7:0] p01_inp;
    reg [7:0] u00;
    reg [7:0] temp_hpc3_v_1_order0;
    reg [7:0] a_share_reg_hpc3_v_1_order0;
    wire [7:0] v01;
    wire [7:0] a_share_neg_hpc3_w_1_order0;
    wire [7:0] temp_hpc3_w_1_order0;
    reg [7:0] w01;
    wire [7:0] u01;
    reg [7:0] temp_hpc3_v_1_order1;
    reg [7:0] a_share_reg_hpc3_v_1_order1;
    wire [7:0] v10;
    wire [7:0] a_share_neg_hpc3_w_1_order1;
    wire [7:0] temp_hpc3_w_1_order1;
    reg [7:0] w10;
    wire [7:0] u10;
    reg [7:0] u11;

    assign a0_inp = a0;
    assign a1_inp = a1;
    assign b0_inp = b0;
    assign b1_inp = b1;
    assign r01_inp = r01;
    assign p01_inp = p01;
    assign v01 = (temp_hpc3_v_1_order0 & a_share_reg_hpc3_v_1_order0);
    assign a_share_neg_hpc3_w_1_order0 = ~a0_inp;
    assign temp_hpc3_w_1_order0 = (a_share_neg_hpc3_w_1_order0 & r01_inp);
    assign u01 = (v01 ^ w01);
    assign v10 = (temp_hpc3_v_1_order1 & a_share_reg_hpc3_v_1_order1);
    assign a_share_neg_hpc3_w_1_order1 = ~a1_inp;
    assign temp_hpc3_w_1_order1 = (a_share_neg_hpc3_w_1_order1 & r01_inp);
    assign u10 = (v10 ^ w10);

    always @(posedge clk) begin
        u00 <= (a0_inp & b0_inp);
        temp_hpc3_v_1_order0 <= (b1_inp ^ r01_inp);
        a_share_reg_hpc3_v_1_order0 <= a0_inp;
        w01 <= (temp_hpc3_w_1_order0 ^ p01_inp);
        temp_hpc3_v_1_order1 <= (b0_inp ^ r01_inp);
        a_share_reg_hpc3_v_1_order1 <= a1_inp;
        w10 <= (temp_hpc3_w_1_order1 ^ p01_inp);
        u11 <= (a1_inp & b1_inp);
        c0 <= (u00 ^ u01);
        c1 <= (u10 ^ u11);
    end

endmodule

src/Testing/HPC3/Share_1/hpc3_tb.v
`timescale 1ns/1ps

module HPC3_tb;

    // Signals
    reg clk;
    reg  [7:0] a0, a1;
    reg  [7:0] b0, b1;
    reg  [7:0] r01, p01;
    wire [7:0] c0, c1;

    integer fd, r;
    integer line_num;
    integer exp_a, exp_b, exp_c;
    reg [8*256:0] header; // to skip header line in CSV

    // Instantiate DUT
    HPC3 uut (
        .clk(clk),
        .a0(a0), .a1(a1),
        .b0(b0), .b1(b1),
        .r01(r01), .p01(p01),
        .c0(c0), .c1(c1)
    );

    // Clock
    initial begin
        clk = 0;
        forever #5 clk = ~clk;
    end

    // Stimulus
    initial begin
        // VCD dump
        $dumpfile("HPC3_tb.vcd");
        $dumpvars(0, HPC3_tb);

        // Open CSV file
        fd = $fopen("test_vectors.csv", "r");
        if (fd == 0) begin
            $display("ERROR: Could not open test_vectors.csv");
            $finish;
        end

        // Skip header
        r = $fgets(header, fd);

        line_num = 0;

        // Read lines until EOF
        while (!$feof(fd)) begin
            line_num = line_num + 1;

            r = $fscanf(fd, "%d,%d,%d,%d,%d,%d,%d,%d,%d,%d\n",
                        a0, a1, b0, b1, r01, p01,
                        exp_a, exp_b, exp_c);

            @(posedge clk); // wait 1 cycle for DUT to compute
            #50;
            if ((c0 ^ c1) === exp_c)
                $display("Line %0d: PASS (a0=%0d a1=%0d b0=%0d b1=%0d) -> c0^c1=%0d expected=%0d",
                         line_num, a0, a1, b0, b1, (c0 ^ c1), exp_c);
            else
                $display("Line %0d: FAIL (a0=%0d a1=%0d b0=%0d b1=%0d c0=%0d, c1=%0d) -> c0^c1=%0d expected=%0d",
                         line_num, a0, a1, b0, b1,c0, c1, (c0 ^ c1), exp_c);
        end

        $fclose(fd);
        $display("All test vectors processed.");
        #20 $finish;
    end

endmodule

src/Testing/HPC3/Share_1/HPC3_tb.vcd
$date
	Thu Aug 28 15:11:13 2025
$end
$version
	Icarus Verilog
$end
$timescale
	1ps
$end
$scope module HPC3_tb $end
$var wire 8 ! c1 [7:0] $end
$var wire 8 " c0 [7:0] $end
$var reg 8 # a0 [7:0] $end
$var reg 8 $ a1 [7:0] $end
$var reg 8 % b0 [7:0] $end
$var reg 8 & b1 [7:0] $end
$var reg 1 ' clk $end
$var reg 2049 ( header [2048:0] $end
$var reg 8 ) p01 [7:0] $end
$var reg 8 * r01 [7:0] $end
$var integer 32 + exp_a [31:0] $end
$var integer 32 , exp_b [31:0] $end
$var integer 32 - exp_c [31:0] $end
$var integer 32 . fd [31:0] $end
$var integer 32 / line_num [31:0] $end
$var integer 32 0 r [31:0] $end
$scope module uut $end
$var wire 8 1 a0 [7:0] $end
$var wire 8 2 a0_inp [7:0] $end
$var wire 8 3 a1 [7:0] $end
$var wire 8 4 a1_inp [7:0] $end
$var wire 8 5 a_share_neg_hpc3_w_1_order0 [7:0] $end
$var wire 8 6 a_share_neg_hpc3_w_1_order1 [7:0] $end
$var wire 8 7 b0 [7:0] $end
$var wire 8 8 b0_inp [7:0] $end
$var wire 8 9 b1 [7:0] $end
$var wire 8 : b1_inp [7:0] $end
$var wire 1 ' clk $end
$var wire 8 ; p01 [7:0] $end
$var wire 8 < p01_inp [7:0] $end
$var wire 8 = r01 [7:0] $end
$var wire 8 > r01_inp [7:0] $end
$var wire 8 ? temp_hpc3_w_1_order0 [7:0] $end
$var wire 8 @ temp_hpc3_w_1_order1 [7:0] $end
$var wire 8 A u01 [7:0] $end
$var wire 8 B u10 [7:0] $end
$var wire 8 C v01 [7:0] $end
$var wire 8 D v10 [7:0] $end
$var reg 8 E a_share_reg_hpc3_v_1_order0 [7:0] $end
$var reg 8 F a_share_reg_hpc3_v_1_order1 [7:0] $end
$var reg 8 G c0 [7:0] $end
$var reg 8 H c1 [7:0] $end
$var reg 8 I temp_hpc3_v_1_order0 [7:0] $end
$var reg 8 J temp_hpc3_v_1_order1 [7:0] $end
$var reg 8 K u00 [7:0] $end
$var reg 8 L u11 [7:0] $end
$var reg 8 M w01 [7:0] $end
$var reg 8 N w10 [7:0] $end
$upscope $end
$upscope $end
$enddefinitions $end
$comment Show the parameter values. $end
$dumpall
$end
#0
$dumpvars
bx N
bx M
bx L
bx K
bx J
bx I
bx H
bx G
bx F
bx E
bx D
bx C
bx B
bx A
b10010000 @
b0 ?
b10110100 >
b10110100 =
b110000 <
b110000 ;
b1110 :
b1110 9
b1000001 8
b1000001 7
b11011010 6
b1000001 5
b100101 4
b100101 3
b10111110 2
b10111110 1
b1001 0
b1 /
b10000000000000000000000000000011 .
b1011 -
b1001111 ,
b10011011 +
b10110100 *
b110000 )
b110000100110000001011000110000100110001001011000110001000110000001011000110001000110001001011000111001000110000001100010010110001110000001100000011000100101100011000010010110001100010001011000110001100001010 (
0'
b1110 &
b1000001 %
b100101 $
b10111110 #
bx "
bx !
$end
#5000
b10000101 B
b100101 D
b10001010 A
b10111010 C
b100 L
b10100000 N
b100101 F
b11110101 J
b110000 M
b10111110 E
b10111010 I
b0 K
1'
#10000
0'
#15000
b10000001 !
b10000001 H
b10001010 "
b10001010 G
1'
#20000
0'
#25000
1'
#30000
0'
#35000
1'
#40000
0'
#45000
1'
#50000
0'
#55000
b11001111 B
b1001000 D
b11000110 A
b1000001 C
b1001000 L
b10000111 N
b1011000 F
b1101100 J
b10000111 M
b1010001 E
b1101101 I
b1000000 K
b110 ?
b110 @
b10100111 6
b10101110 5
1'
b1 -
b1 ,
b1001 +
b10000001 <
b10000001 )
b10000001 ;
b110 >
b110 *
b110 =
b1101011 :
b1101011 &
b1101011 9
b1101010 8
b1101010 %
b1101010 7
b1011000 4
b1011000 $
b1011000 3
b1010001 2
b1010001 #
b1010001 1
b10 /
#60000
0'
#65000
b10000111 !
b10000111 H
b10000110 "
b10000110 G
1'
#70000
0'
#75000
1'
#80000
0'
#85000
1'
#90000
0'
#95000
1'
#100000
0'
#105000
b1001 B
b1010100 D
b1011101 A
b0 C
b10000 L
b1011101 N
b1010100 F
b1111110 J
b1011101 M
b1001000 E
b110101 I
b1001000 K
b10 @
b10101011 6
b10110111 5
1'
b1000 -
b1001011 ,
b11100 +
b1011011 <
b1011011 )
b1011011 ;
b110011 :
b110011 &
b110011 9
b1111000 8
b1111000 %
b1111000 7
b1010100 4
b1010100 $
b1010100 3
b1001000 2
b1001000 #
b1001000 1
b11 /
#110000
0'
#115000
b1101 B
b11001 !
b11001 H
b10101 "
b10101 G
b1011001 N
1'
#120000
0'
#125000
b11101 !
b11101 H
1'
#130000
0'
#135000
1'
#140000
0'
#145000
1'
#150000
0'
#155000
b1010111 B
b1 D
b1000110 A
b10000 C
b11000 L
b1010110 N
b1011101 F
b10100011 J
b1010110 M
b11100 E
b110000 I
b1000 K
b100010 ?
b100010 @
b10100010 6
b11100011 5
1'
b1 -
b10010011 ,
b1000001 +
b1110100 <
b1110100 )
b1110100 ;
b101010 >
b101010 *
b101010 =
b11010 :
b11010 &
b11010 9
b10001001 8
b10001001 %
b10001001 7
b1011101 4
b1011101 $
b1011101 3
b11100 2
b11100 #
b11100 1
b100 /
#160000
0'
#165000
b1001111 !
b1001111 H
b1001110 "
b1001110 G
1'
#170000
0'
#175000
1'
#180000
0'
#185000
1'
#190000
0'
#195000
1'
#200000
0'
#205000
b1001000 B
b0 D
b1100110 A
b101110 C
b0 L
b1001000 N
b10011000 F
b1000110 J
b1001000 M
b111110 E
b1101110 I
b101100 K
b0 ?
b1100111 6
b11000001 5
1'
b100000 -
b101000 ,
b10100110 +
b1101010 <
b1101010 )
b1101010 ;
b1000100 :
b1000100 &
b1000100 9
b1101100 8
b1101100 %
b1101100 7
b10011000 4
b10011000 $
b10011000 3
b111110 2
b111110 #
b111110 1
b101 /
#210000
0'
#215000
b1000100 A
b1001000 !
b1001000 H
b1001010 "
b1001010 G
b1101010 M
1'
#220000
0'
#225000
b1101000 "
b1101000 G
1'
#230000
0'
#235000
1'
#240000
0'
#245000
1'
#250000
0'
#255000
b1100111 B
b100000 D
b1110111 A
b10110 C
b1000111 N
b100000 F
b10111110 J
b1100001 M
b10111 E
b1110110 I
b10000 K
b101000 ?
b1110 @
b11011111 6
b11101000 5
1'
b0 -
b11001000 ,
b110111 +
b1001001 <
b1001001 )
b1001001 ;
b101110 >
b101110 *
b101110 =
b1011000 :
b1011000 &
b1011000 9
b10010000 8
b10010000 %
b10010000 7
b100000 4
b100000 $
b100000 3
b10111 2
b10111 #
b10111 1
b110 /
#260000
0'
#265000
b1100111 !
b1100111 H
b1100111 "
b1100111 G
1'
#270000
0'
#275000
1'
#280000
0'
#285000
1'
#290000
0'
#295000
1'
#300000
0'
#305000
b1010100 B
b0 D
b10101 A
b1000011 C
b10000000 L
b1010100 N
b10000000 F
b1010010 J
b1010110 M
b1010111 E
b11100011 I
b1010000 K
b100000 ?
b100010 @
b1111111 6
b10101000 5
1'
b10010001 -
b10110001 ,
b11010111 +
b1110110 <
b1110110 )
b1110110 ;
b100010 >
b100010 *
b100010 =
b11000001 :
b11000001 &
b11000001 9
b1110000 8
b1110000 %
b1110000 7
b10000000 4
b10000000 $
b10000000 3
b1010111 2
b1010111 #
b1010111 1
b111 /
#310000
0'
#315000
b11010100 !
b11010100 H
b1000101 "
b1000101 G
1'
#320000
0'
#325000
1'
#330000
0'
#335000
1'
#340000
0'
#345000
1'
#350000
0'
#355000
b110001 B
b111000 D
b1110001 A
b1001000 C
b0 L
b1001 N
b111000 F
b111011 J
b111001 M
b1001000 E
b11111001 I
b0 K
b110001 ?
b1 @
b11000111 6
b10110111 5
1'
b1000000 -
b11000010 ,
b1110000 +
b1000 <
b1000 )
b1000 ;
b111001 >
b111001 *
b111001 =
b11000000 :
b11000000 &
b11000000 9
b10 8
b10 %
b10 7
b111000 4
b111000 $
b111000 3
b1001000 2
b1001000 #
b1001000 1
b1000 /
#360000
0'
#365000
b110001 !
b110001 H
b1110001 "
b1110001 G
1'
#370000
0'
#375000
1'
#380000
0'
#385000
1'
#390000
0'
#395000
1'
#400000
0'
#405000
b1110001 B
b100011 D
b1110010 A
b100000 C
b100010 L
b1010010 N
b100011 F
b111111 J
b1010010 M
b100000 E
b10100110 I
b100000 K
b1100 ?
b1100 @
b11011100 6
b11011111 5
1'
b1 -
b10011001 ,
b11 +
b1011110 <
b1011110 )
b1011110 ;
b1100 >
b1100 *
b1100 =
b10101010 :
b10101010 &
b10101010 9
b110011 8
b110011 %
b110011 7
b100011 4
b100011 $
b100011 3
b100000 2
b100000 #
b100000 1
b1001 /
#410000
0'
#415000
b1010011 !
b1010011 H
b1010010 "
b1010010 G
1'
#420000
0'
#425000
1'
#430000
0'
#435000
1'
#440000
0'
#445000
1'
#450000
0'
#455000
b1111001 B
b11000 D
b111000 A
b10101 C
b0 L
b1100001 N
b11000 F
b10011000 J
b101101 M
b1010101 E
b10011101 I
b1000100 K
b1000 ?
b1000100 @
b11100111 6
b10101010 5
1'
b101 -
b101 ,
b1001101 +
b100101 <
b100101 )
b100101 ;
b1011100 >
b1011100 *
b1011100 =
b11000001 :
b11000001 &
b11000001 9
b11000100 8
b11000100 %
b11000100 7
b11000 4
b11000 $
b11000 3
b1010101 2
b1010101 #
b1010101 1
b1010 /
#460000
0'
#465000
b1111001 !
b1111001 H
b1111100 "
b1111100 G
1'
#470000
0'
#475000
1'
#480000
0'
#485000
1'
#490000
0'
#495000
1'
#500000
0'
#505000
b10011100 B
b1010100 D
b11011000 A
b10000 C
b100 L
b11001000 N
b1110100 F
b11011111 J
b11001000 M
b110000 E
b10100 I
b0 K
b10001010 ?
b10001010 @
b10001011 6
b11001111 5
1'
b1000000 -
b11001011 ,
b1000100 +
b1000010 <
b1000010 )
b1000010 ;
b10011010 >
b10011010 *
b10011010 =
b10001110 :
b10001110 &
b10001110 9
b1000101 8
b1000101 %
b1000101 7
b1110100 4
b1110100 $
b1110100 3
b110000 2
b110000 #
b110000 1
b1011 /
#510000
0'
#515000
b10011000 !
b10011000 H
b11011000 "
b11011000 G
1'
#520000
0'
#525000
1'
#530000
0'
#535000
1'
#540000
0'
#545000
1'
#550000
0'
#555000
b10011010 B
b101000 D
b111 A
b101 C
b1101 L
b10110010 N
b10111111 F
b101000 J
b10 M
b1111 E
b11110101 I
b10110000 ?
b0 @
b1000000 6
b11110000 5
1'
b10010000 -
b11011101 ,
b10110000 +
b10110010 <
b10110010 )
b10110010 ;
b10111000 >
b10111000 *
b10111000 =
b1001101 :
b1001101 &
b1001101 9
b10010000 8
b10010000 %
b10010000 7
b10111111 4
b10111111 $
b10111111 3
b1111 2
b1111 #
b1111 1
b1100 /
#560000
0'
#565000
b10010111 !
b10010111 H
b111 "
b111 G
1'
#570000
0'
#575000
1'
#580000
0'
#585000
1'
#590000
0'
#595000
1'
#600000
0'
#605000
b1001010 B
b110101 D
b10111011 A
b0 C
b101 L
b1111111 N
b110111 F
b1111101 J
b10111011 M
b11000011 E
b0 I
b10000000 K
b100 ?
b11000000 @
b11001000 6
b111100 5
1'
b1110100 -
b1111101 ,
b11110100 +
b10111111 <
b10111111 )
b10111111 ;
b11000101 >
b11000101 *
b11000101 =
b11000101 :
b11000101 &
b11000101 9
b10111000 8
b10111000 %
b10111000 7
b110111 4
b110111 $
b110111 3
b11000011 2
b11000011 #
b11000011 1
b1101 /
#610000
0'
#615000
b1001111 !
b1001111 H
b111011 "
b111011 G
1'
#620000
0'
#625000
1'
#630000
0'
#635000
1'
#640000
0'
#645000
1'
#650000
0'
#655000
b11111011 B
b11100 D
b1111011 A
b11010 C
b11101 L
b11100111 N
b11101 F
b11011110 J
b1100001 M
b10011011 E
b1011010 I
b11001 K
b1000100 ?
b11000010 @
b11100010 6
b1100100 5
1'
b10000100 -
b10000100 ,
b10000110 +
b100101 <
b100101 )
b100101 ;
b11000111 >
b11000111 *
b11000111 =
b10011101 :
b10011101 &
b10011101 9
b11001 8
b11001 %
b11001 7
b11101 4
b11101 $
b11101 3
b10011011 2
b10011011 #
b10011011 1
b1110 /
#660000
0'
#665000
b11100110 !
b11100110 H
b1100010 "
b1100010 G
1'
#670000
0'
#675000
1'
#680000
0'
#685000
1'
#690000
0'
#695000
1'
#700000
0'
#705000
b11111001 B
b1 D
b11011000 A
b110000 C
b0 L
b11111000 N
b100001 F
b10001101 J
b11101000 M
b110010 E
b1110100 I
b110000 K
b10000000 ?
b10010000 @
b11011110 6
b11001101 5
1'
b10001 -
b11111001 ,
b10011 +
b1101000 <
b1101000 )
b1101000 ;
b10110000 >
b10110000 *
b10110000 =
b11000100 :
b11000100 &
b11000100 9
b111101 8
b111101 %
b111101 7
b100001 4
b100001 $
b100001 3
b110010 2
b110010 #
b110010 1
b1111 /
#710000
0'
#715000
b11111001 !
b11111001 H
b11101000 "
b11101000 G
1'
#720000
0'
#725000
1'
#730000
0'
#735000
1'
#740000
0'
#745000
1'
#750000
0'
#755000
b11101101 B
b100 D
b11101101 A
b10100100 C
b10 L
b11101001 N
b10111 F
b1100 J
b1001001 M
b10110111 E
b10100100 I
b10100010 K
b0 ?
b10100000 @
b11101000 6
b1001000 5
1'
b10100000 -
b10101000 ,
b10100000 +
b1001001 <
b1001001 )
b1001001 ;
b10100110 >
b10100110 *
b10100110 =
b10 :
b10 &
b10 9
b10101010 8
b10101010 %
b10101010 7
b10111 4
b10111 $
b10111 3
b10110111 2
b10110111 #
b10110111 1
b10000 /
#760000
0'
#765000
b11101111 !
b11101111 H
b1001111 "
b1001111 G
1'
#770000
0'
#775000
1'
#780000
0'
#785000
1'
#790000
0'
#795000
1'
#800000
0'
#805000
b11000001 B
b11 D
b11000001 A
b100 C
b11 L
b11000010 N
b10000011 F
b1000111 J
b11000101 M
b1000100 E
b1100 I
b1000000 K
b11 ?
b100 @
b1111100 6
b10111011 5
1'
b1000011 -
b1001011 ,
b11000111 +
b11000110 <
b11000110 )
b11000110 ;
b111 >
b111 *
b111 =
b1011 :
b1011 &
b1011 9
b1000000 8
b1000000 %
b1000000 7
b10000011 4
b10000011 $
b10000011 3
b1000100 2
b1000100 #
b1000100 1
b10001 /
#810000
0'
#815000
b11000010 !
b11000010 H
b10000001 "
b10000001 G
1'
#820000
0'
#825000
1'
#830000
0'
#835000
1'
#840000
0'
#845000
1'
#850000
0'
#855000
b1010010 B
b1 D
b1011010 A
b10001001 C
b0 L
b1010011 N
b1 F
b10010111 J
b11010011 M
b10001011 E
b11011101 I
b10 K
b10100 ?
b10010100 @
b11111110 6
b1110100 5
1'
b1010 -
b1001010 ,
b10001010 +
b11000111 <
b11000111 )
b11000111 ;
b10010101 >
b10010101 *
b10010101 =
b1001000 :
b1001000 &
b1001000 9
b10 8
b10 %
b10 7
b1 4
b1 $
b1 3
b10001011 2
b10001011 #
b10001011 1
b10010 /
#860000
0'
#865000
b1010010 !
b1010010 H
b1011000 "
b1011000 G
1'
#870000
0'
#875000
1'
#880000
0'
#885000
1'
#890000
0'
#895000
1'
#900000
0'
#905000
b10101000 B
b10000 D
b10101111 A
b11110 C
b10101 L
b10111000 N
b110101 F
b10010 J
b10110001 M
b111110 E
b1011110 I
b11010 K
b1 ?
b1000 @
b11001010 6
b11000001 5
1'
b1000 -
b1001100 ,
b1011 +
b10110000 <
b10110000 )
b10110000 ;
b1001 >
b1001 *
b1001 =
b1010111 :
b1010111 &
b1010111 9
b11011 8
b11011 %
b11011 7
b110101 4
b110101 $
b110101 3
b111110 2
b111110 #
b111110 1
b10011 /
#910000
0'
#915000
b10111101 !
b10111101 H
b10110101 "
b10110101 G
1'
#920000
0'
#925000
1'
#930000
0'
#935000
1'
#940000
0'
#945000
1'
#950000
0'
#955000
b101011 B
b1 D
b1100001 A
b1001001 C
b0 L
b101010 N
b1001 F
b10010011 J
b101000 M
b1001011 E
b11001101 I
b1000 K
b10010000 ?
b10010010 @
b11110110 6
b10110100 5
1'
b1000010 -
b1011110 ,
b1000010 +
b10111000 <
b10111000 )
b10111000 ;
b10011011 >
b10011011 *
b10011011 =
b1010110 :
b1010110 &
b1010110 9
b1000 8
b1000 %
b1000 7
b1001 4
b1001 $
b1001 3
b1001011 2
b1001011 #
b1001011 1
b10100 /
#960000
0'
#965000
b101011 !
b101011 H
b1101001 "
b1101001 G
1'
#970000
0'
#975000
1'
#980000
0'
#985000
1'
#990000
0'
#995000
1'
#1000000
0'
#1005000
b11110101 B
b10001010 D
b11011011 A
b10100000 C
b1000 L
b1111111 N
b10001010 F
b10001011 J
b1111011 M
b10111110 E
b11100001 I
b110 K
b0 ?
b100 @
b1110101 6
b1000001 5
1'
b100000 -
b1101010 ,
b110100 +
b1111011 <
b1111011 )
b1111011 ;
b10001100 >
b10001100 *
b10001100 =
b1101101 :
b1101101 &
b1101101 9
b111 8
b111 %
b111 7
b10001010 4
b10001010 $
b10001010 3
b10111110 2
b10111110 #
b10111110 1
b10101 /
#1010000
0'
#1015000
b11111101 !
b11111101 H
b11011101 "
b11011101 G
1'
#1020000
0'
#1025000
1'
#1030000
0'
#1035000
1'
#1040000
0'
#1045000
1'
#1050000
0'
#1055000
b10010000 B
b100 D
b10110011 A
b10000111 C
b110 L
b10010100 N
b111 F
b10011100 J
b110100 M
b10110111 E
b10000111 I
b110101 K
b1000 ?
b10101000 @
b11111000 6
b1001000 5
1'
b10000 -
b11011 ,
b10110000 +
b111100 <
b111100 )
b111100 ;
b10101001 >
b10101001 *
b10101001 =
b101110 :
b101110 &
b101110 9
b110101 8
b110101 %
b110101 7
b111 4
b111 $
b111 3
b10110111 2
b10110111 #
b10110111 1
b10110 /
#1060000
0'
#1065000
b10010110 !
b10010110 H
b10000110 "
b10000110 G
1'
#1070000
0'
#1075000
1'
#1080000
0'
#1085000
1'
#1090000
0'
#1095000
1'
#1100000
0'
#1105000
b11100110 B
b1000 D
b11101111 A
b1 C
b0 L
b11101110 N
b111001 F
b10001010 J
b11101110 M
b101011 E
b1000101 I
b1011 K
b10000000 ?
b10000000 @
b11000110 6
b11010100 5
1'
b10 -
b11001111 ,
b10010 +
b1101110 <
b1101110 )
b1101110 ;
b10000001 >
b10000001 *
b10000001 =
b11000100 :
b11000100 &
b11000100 9
b1011 8
b1011 %
b1011 7
b111001 4
b111001 $
b111001 3
b101011 2
b101011 #
b101011 1
b10111 /
#1110000
0'
#1115000
b11100110 !
b11100110 H
b11100100 "
b11100100 G
1'
#1120000
0'
#1125000
1'
#1130000
0'
#1135000
1'
#1140000
0'
#1145000
1'
#1150000
0'
#1155000
b1100000 B
b101001 D
b11010010 A
b10000010 C
b10101100 L
b1001001 N
b10111111 F
b1101001 J
b1010000 M
b11000010 E
b10110111 I
b1000010 K
b11001 ?
b0 @
b1000000 6
b111101 5
1'
b1011100 -
b11011110 ,
b1111101 +
b1001001 <
b1001001 )
b1001001 ;
b11011 >
b11011 *
b11011 =
b10101100 :
b10101100 &
b10101100 9
b1110010 8
b1110010 %
b1110010 7
b10111111 4
b10111111 $
b10111111 3
b11000010 2
b11000010 #
b11000010 1
b11000 /
#1160000
0'
#1165000
b11001100 !
b11001100 H
b10010000 "
b10010000 G
1'
#1170000
0'
#1175000
1'
#1180000
0'
#1185000
1'
#1190000
0'
#1195000
1'
#1200000
0'
#1205000
b10111110 B
b10000 D
b111110 A
b10011 C
b10100 L
b10101110 N
b110100 F
b11011000 J
b101101 M
b10010011 E
b10111 I
b10011 K
b1000 ?
b10001011 @
b11001011 6
b1101100 5
1'
b10000111 -
b11001111 ,
b10100111 +
b100101 <
b100101 )
b100101 ;
b10001011 >
b10001011 *
b10001011 =
b10011100 :
b10011100 &
b10011100 9
b1010011 8
b1010011 %
b1010011 7
b110100 4
b110100 $
b110100 3
b10010011 2
b10010011 #
b10010011 1
b11001 /
#1210000
0'
#1215000
b10101010 !
b10101010 H
b101101 "
b101101 G
1'
#1220000
0'
#1225000
1'
#1230000
0'
#1235000
1'
#1240000
0'
#1245000
1'
#1250000
0'
#1255000
b11010111 B
b10000000 D
b1011111 A
b1001 C
b0 L
b1010111 N
b10000000 F
b10001010 J
b1010110 M
b1011001 E
b1011 I
b1001 K
b100100 ?
b100101 @
b1111111 6
b10100110 5
1'
b10000001 -
b10000001 ,
b11011001 +
b1110010 <
b1110010 )
b1110010 ;
b100101 >
b100101 *
b100101 =
b101110 :
b101110 &
b101110 9
b10101111 8
b10101111 %
b10101111 7
b10000000 4
b10000000 $
b10000000 3
b1011001 2
b1011001 #
b1011001 1
b11010 /
#1260000
0'
#1265000
b11010111 !
b11010111 H
b1010110 "
b1010110 G
1'
#1270000
0'
#1275000
1'
#1280000
0'
#1285000
1'
#1290000
0'
#1295000
1'
#1300000
0'
#1305000
b10110011 B
b1000 D
b11001 A
b10100001 C
b10101000 L
b10111011 N
b10101010 F
b1001000 J
b10111000 M
b10101001 E
b10100011 I
b1 K
b110 ?
b101 @
b1010101 6
b1010110 5
1'
b11 -
b11101011 ,
b11 +
b10111110 <
b10111110 )
b10111110 ;
b1111 >
b1111 *
b1111 =
b10101100 :
b10101100 &
b10101100 9
b1000111 8
b1000111 %
b1000111 7
b10101010 4
b10101010 $
b10101010 3
b10101001 2
b10101001 #
b10101001 1
b11011 /
#1310000
0'
#1315000
b11011 !
b11011 H
b11000 "
b11000 G
1'
#1320000
0'
#1325000
1'
#1330000
0'
#1335000
1'
#1340000
0'
#1345000
1'
#1350000
0'
#1355000
b10100100 B
b101110 A
b10000000 C
b0 L
b10101100 N
b1000 F
b101101 J
b10101110 M
b10110110 E
b11000001 I
b100110 K
b1 ?
b11 @
b11110111 6
b1001001 5
1'
b10101100 -
b11101100 ,
b10111110 +
b10101111 <
b10101111 )
b10101111 ;
b11 >
b11 *
b11 =
b11000010 :
b11000010 &
b11000010 9
b101110 8
b101110 %
b101110 7
b1000 4
b1000 $
b1000 3
b10110110 2
b10110110 #
b10110110 1
b11100 /
#1360000
0'
#1365000
b10100100 !
b10100100 H
b1000 "
b1000 G
1'
#1370000
0'
#1375000
1'
#1380000
0'
#1385000
1'
#1390000
0'
#1395000
1'
#1400000
0'
#1405000
b111000 B
b1 D
b11110 A
b1 C
b10001 L
b111001 N
b10010011 F
b101 J
b11111 M
b110101 E
b11 I
b110001 K
b1000010 ?
b1100100 @
b1101100 6
b11001010 5
1'
b110 -
b110 ,
b10100110 +
b1011101 <
b1011101 )
b1011101 ;
b1110110 >
b1110110 *
b1110110 =
b1110101 :
b1110101 &
b1110101 9
b1110011 8
b1110011 %
b1110011 7
b10010011 4
b10010011 $
b10010011 3
b110101 2
b110101 #
b110101 1
b11101 /
#1410000
0'
#1415000
b101001 !
b101001 H
b101111 "
b101111 G
1'
#1420000
0'
#1425000
1'
#1430000
0'
#1435000
1'
#1440000
0'
#1445000
1'
#1450000
0'
#1455000
b11111001 B
b1010 D
b11110001 A
b10100010 C
b1001 L
b11110011 N
b1111 F
b111010 J
b1010011 M
b10111111 E
b11100010 I
b10010001 K
b0 ?
b10100000 @
b11110000 6
b1000000 5
1'
b10010000 -
b11011000 ,
b10110000 +
b1010011 <
b1010011 )
b1010011 ;
b10101011 >
b10101011 *
b10101011 =
b1001001 :
b1001001 &
b1001001 9
b10010001 8
b10010001 %
b10010001 7
b1111 4
b1111 $
b1111 3
b10111111 2
b10111111 #
b10111111 1
b11110 /
#1460000
0'
#1465000
b11110000 !
b11110000 H
b1100000 "
b1100000 G
1'
#1470000
0'
#1475000
1'
#1480000
0'
#1485000
1'
#1490000
0'
#1495000
1'
#1500000
0'
#1505000
b10101101 B
b1000 D
b10010101 A
b0 C
b1000 L
b10100101 N
b1001 F
b10011010 J
b10010101 M
b111100 E
b10000010 I
b100000 K
b110000 @
b11110110 6
b11000011 5
1'
b10000 -
b11000 ,
b110101 +
b10010101 <
b10010101 )
b10010101 ;
b111000 >
b111000 *
b111000 =
b10111010 :
b10111010 &
b10111010 9
b10100010 8
b10100010 %
b10100010 7
b1001 4
b1001 $
b1001 3
b111100 2
b111100 #
b111100 1
b11111 /
#1510000
0'
#1515000
b10100101 !
b10100101 H
b10110101 "
b10110101 G
1'
#1520000
0'
#1525000
1'
#1530000
0'
#1535000
1'
#1540000
0'
#1545000
1'
#1550000
0'
#1555000
b11100110 B
b10100101 D
b11000001 A
b10000 C
b111 L
b1000011 N
b10101111 F
b11100101 J
b11010001 M
b110001 E
b11010100 I
b110000 K
b10000010 ?
b10000 @
b1010000 6
b11001110 5
1'
b110001 ,
b10011110 +
b1010011 <
b1010011 )
b1010011 ;
b10010011 >
b10010011 *
b10010011 =
b1000111 :
b1000111 &
b1000111 9
b1110110 8
b1110110 %
b1110110 7
b10101111 4
b10101111 $
b10101111 3
b110001 2
b110001 #
b110001 1
b100000 /
#1560000
0'
#1565000
b11100001 !
b11100001 H
b11110001 "
b11110001 G
1'
#1570000
0'
#1575000
1'
#1580000
0'
#1585000
1'
#1590000
0'
#1595000
1'
#1600000
0'
#1605000
b10000100 B
b0 D
b10101100 A
b101100 C
b0 L
b10000100 N
b10000000 F
b1101110 J
b10000000 M
b111100 E
b101100 I
b101000 K
b1000011 ?
b1000111 @
b1111111 6
b11000011 5
1'
b0 -
b1000010 ,
b10111100 +
b11000011 <
b11000011 )
b11000011 ;
b1000111 >
b1000111 *
b1000111 =
b1101011 :
b1101011 &
b1101011 9
b101001 8
b101001 %
b101001 7
b10000000 4
b10000000 $
b10000000 3
b111100 2
b111100 #
b111100 1
b100001 /
#1610000
0'
