src/Testing/HPC1/Share_1/hpc1.v
module HPC1(
    clk,
    a0,
    a1,
    b0,
    b1,
    rand_0,
    prand_01,
    c0,
    c1
);
//INPUTS
    input clk;
    input  [7:0] a0;
    input  [7:0] a1;
    input  [7:0] b0;
    input  [7:0] b1;
    input  [7:0] rand_0;
    input  [7:0] prand_01;
//OUTPUTS
    output reg  [7:0] c0;
    output reg  [7:0] c1;
//Intermediate values
    wire [7:0] a0_inp;
    wire [7:0] a1_inp;
    wire [7:0] b0_inp;
    wire [7:0] b1_inp;
    wire [7:0] rand_0_inp;
    wire [7:0] prand_01_inp;
    reg [7:0] b_share__hpc1_same_shares_1_order0;
    reg [7:0] a0_inp_reg;
    wire [7:0] v00;
    reg [7:0] b_share__hpc1_cross_domain_1_order0;
    wire [7:0] a_and_b_hpc1_cross_domain_1_order0;
    reg [7:0] prand_01_inp_reg;
    wire [7:0] v01;
    reg [7:0] b_share__hpc1_cross_domain_1_order1;
    reg [7:0] a1_inp_reg;
    wire [7:0] a_and_b_hpc1_cross_domain_1_order1;
    wire [7:0] v10;
    reg [7:0] b_share__hpc1_same_shares_1_order1;
    wire [7:0] v11;
    wire [7:0] z69_assgn69;
    wire [7:0] z71_assgn71;

    assign a0_inp = a0;
    assign a1_inp = a1;
    assign b0_inp = b0;
    assign b1_inp = b1;
    assign rand_0_inp = rand_0;
    assign prand_01_inp = prand_01;
    assign v00 = (a0_inp_reg & b_share__hpc1_same_shares_1_order0);
    assign a_and_b_hpc1_cross_domain_1_order0 = (a0_inp_reg & b_share__hpc1_cross_domain_1_order0);
    assign v01 = (a_and_b_hpc1_cross_domain_1_order0 ^ prand_01_inp_reg);
    assign a_and_b_hpc1_cross_domain_1_order1 = (a1_inp_reg & b_share__hpc1_cross_domain_1_order1);
    assign v10 = (a_and_b_hpc1_cross_domain_1_order1 ^ prand_01_inp_reg);
    assign v11 = (a1_inp_reg & b_share__hpc1_same_shares_1_order1);
    assign z69_assgn69 = (v00 ^ v01);
    assign z71_assgn71 = (v10 ^ v11);

    always @(posedge clk) begin
        b_share__hpc1_same_shares_1_order0 <= (b0_inp ^ rand_0_inp);
        a0_inp_reg <= a0_inp;
        b_share__hpc1_cross_domain_1_order0 <= (b1_inp ^ rand_0_inp);
        prand_01_inp_reg <= prand_01_inp;
        b_share__hpc1_cross_domain_1_order1 <= (b0_inp ^ rand_0_inp);
        a1_inp_reg <= a1_inp;
        b_share__hpc1_same_shares_1_order1 <= (b1_inp ^ rand_0_inp);
        c0 <= z69_assgn69;
        c1 <= z71_assgn71;
    end

endmodule

src/Testing/HPC1/Share_1/hpc1_tb.v
`timescale 1ns/1ps

module HPC1_tb;

    // Signals
    reg clk;
    reg  [7:0] a0, a1;
    reg  [7:0] b0, b1;
    reg  [7:0] rand_0, prand_01;
    wire [7:0] c0, c1;

    integer fd, r;
    integer line_num;
    integer exp_a, exp_b, exp_c;
    reg [8*256:0] header; // to skip header line in CSV

    // Instantiate DUT
    HPC1 uut (
        .clk(clk),
        .a0(a0), .a1(a1),
        .b0(b0), .b1(b1),
        .rand_0(rand_0), .prand_01(prand_01),
        .c0(c0), .c1(c1)
    );

    // Clock
    initial begin
        clk = 0;
        forever #5 clk = ~clk;
    end

    // Stimulus
    initial begin
        // VCD dump
        $dumpfile("HPC1_tb.vcd");
        $dumpvars(0, HPC1_tb);

        // Open CSV file
        fd = $fopen("test_vectors.csv", "r");
        if (fd == 0) begin
            $display("ERROR: Could not open test_vectors.csv");
            $finish;
        end

        // Skip header
        r = $fgets(header, fd);

        line_num = 0;

        // Read lines until EOF
        while (!$feof(fd)) begin
            line_num = line_num + 1;

            r = $fscanf(fd, "%d,%d,%d,%d,%d,%d,%d,%d,%d\n",
                        a0, a1, b0, b1, rand_0, prand_01,
                        exp_a, exp_b, exp_c);

            @(posedge clk); // wait 1 cycle for DUT to compute
            #40;
            if ((c0 ^ c1) === exp_c)
                $display("Line %0d: PASS (a0=%0d a1=%0d b0=%0d b1=%0d) -> c0^c1=%0d expected=%0d",
                         line_num, a0, a1, b0, b1, (c0 ^ c1), exp_c);
            else
                $display("Line %0d: FAIL (a0=%0d a1=%0d b0=%0d b1=%0d) -> c0^c1=%0d expected=%0d",
                         line_num, a0, a1, b0, b1, (c0 ^ c1), exp_c);
        end

        $fclose(fd);
        $display("All test vectors processed.");
        #20 $finish;
    end

endmodule

src/Testing/HPC1/Share_1/HPC1_tb.vcd
$date
	Wed Oct 29 18:56:19 2025
$end
$version
	Icarus Verilog
$end
$timescale
	1ps
$end
$scope module HPC1_tb $end
$var wire 8 ! c1 [7:0] $end
$var wire 8 " c0 [7:0] $end
$var reg 8 # a0 [7:0] $end
$var reg 8 $ a1 [7:0] $end
$var reg 8 % b0 [7:0] $end
$var reg 8 & b1 [7:0] $end
$var reg 1 ' clk $end
$var reg 2049 ( header [2048:0] $end
$var reg 8 ) prand_01 [7:0] $end
$var reg 8 * rand_0 [7:0] $end
$var integer 32 + exp_a [31:0] $end
$var integer 32 , exp_b [31:0] $end
$var integer 32 - exp_c [31:0] $end
$var integer 32 . fd [31:0] $end
$var integer 32 / line_num [31:0] $end
$var integer 32 0 r [31:0] $end
$scope module uut $end
$var wire 8 1 a0 [7:0] $end
$var wire 8 2 a0_inp [7:0] $end
$var wire 8 3 a1 [7:0] $end
$var wire 8 4 a1_inp [7:0] $end
$var wire 8 5 a_and_b_hpc1_cross_domain_1_order0 [7:0] $end
$var wire 8 6 a_and_b_hpc1_cross_domain_1_order1 [7:0] $end
$var wire 8 7 b0 [7:0] $end
$var wire 8 8 b0_inp [7:0] $end
$var wire 8 9 b1 [7:0] $end
$var wire 8 : b1_inp [7:0] $end
$var wire 1 ' clk $end
$var wire 8 ; prand_01 [7:0] $end
$var wire 8 < prand_01_inp [7:0] $end
$var wire 8 = rand_0 [7:0] $end
$var wire 8 > rand_0_inp [7:0] $end
$var wire 8 ? v00 [7:0] $end
$var wire 8 @ v01 [7:0] $end
$var wire 8 A v10 [7:0] $end
$var wire 8 B v11 [7:0] $end
$var wire 8 C z69_assgn69 [7:0] $end
$var wire 8 D z71_assgn71 [7:0] $end
$var reg 8 E a0_inp_reg [7:0] $end
$var reg 8 F a1_inp_reg [7:0] $end
$var reg 8 G b_share__hpc1_cross_domain_1_order0 [7:0] $end
$var reg 8 H b_share__hpc1_cross_domain_1_order1 [7:0] $end
$var reg 8 I b_share__hpc1_same_shares_1_order0 [7:0] $end
$var reg 8 J b_share__hpc1_same_shares_1_order1 [7:0] $end
$var reg 8 K c0 [7:0] $end
$var reg 8 L c1 [7:0] $end
$var reg 8 M prand_01_inp_reg [7:0] $end
$upscope $end
$upscope $end
$enddefinitions $end
$comment Show the parameter values. $end
$dumpall
$end
#0
$dumpvars
bx M
bx L
bx K
bx J
bx I
bx H
bx G
bx F
bx E
bx D
bx C
bx B
bx A
bx @
bx ?
b11101 >
b11101 =
b11110011 <
b11110011 ;
b11000000 :
b11000000 9
b10000111 8
b10000111 7
bx 6
bx 5
b111101 4
b111101 3
b1100100 2
b1100100 1
b1001 0
b1 /
b10000000000000000000000000000011 .
b1000001 -
b1000111 ,
b1011001 +
b11101 *
b11110011 )
b1100001001100000010110001100001001100010010110001100010001100000010110001100010001100010010110001110010011000010110111001100100010111110011000000101100011100000111001001100001011011100110010001011111001100000011000100101100011000010010110001100010001011000110001100001010 (
0'
b11000000 &
b10000111 %
b111101 $
b1100100 #
bx "
bx !
$end
#5000
b11110110 D
b11101011 A
b10110111 C
b11101 B
b11000 6
b10110111 @
b1000100 5
b0 ?
b11011101 J
b111101 F
b10011010 H
b11110011 M
b11011101 G
b1100100 E
b10011010 I
1'
#10000
0'
#15000
b11110110 !
b11110110 L
b10110111 "
b10110111 K
1'
#20000
0'
#25000
1'
#30000
0'
#35000
1'
#40000
0'
#45000
b11101000 D
b10101011 C
b101 B
b100 6
b11101101 A
b11101001 @
b0 5
b1000010 ?
b100101 J
b101 F
b11100110 H
b11101001 M
b100101 G
b1001010 E
b11100110 I
1'
b1000011 -
b11000011 ,
b1001111 +
b11101001 <
b11101001 )
b11101001 ;
b100001 >
b100001 *
b100001 =
b100 :
b100 &
b100 9
b11000111 8
b11000111 %
b11000111 7
b101 4
b101 $
b101 3
b1001010 2
b1001010 #
b1001010 1
b10 /
#50000
0'
#55000
b11101000 !
b11101000 L
b10101011 "
b10101011 K
1'
#60000
0'
#65000
1'
#70000
0'
#75000
1'
#80000
0'
#85000
b10101101 D
b10101101 C
b1001100 B
b11100001 A
b10001001 @
b1101100 5
b100100 ?
b11101101 J
b1001110 F
b100100 H
b11100101 M
b11101101 G
b1111110 E
b100100 I
1'
b0 -
b11001001 ,
b110000 +
b11100101 <
b11100101 )
b11100101 ;
b1001 >
b1001 *
b1001 =
b11100100 :
b11100100 &
b11100100 9
b101101 8
b101101 %
b101101 7
b1001110 4
b1001110 $
b1001110 3
b1111110 2
b1111110 #
b1111110 1
b11 /
#90000
0'
#95000
b10101101 !
b10101101 L
b10101101 "
b10101101 K
1'
#100000
0'
#105000
1'
#110000
0'
#115000
1'
#120000
0'
#125000
b1110011 D
b110011 C
b1000100 B
b1000 6
b110111 A
b111011 @
b100 5
b1000 ?
b11000100 J
b1000 H
b111111 M
b11000100 G
b11111 E
b1000 I
1'
b1000000 -
b11001100 ,
b1010001 +
b111111 <
b111111 )
b111111 ;
b11101010 >
b11101010 *
b11101010 =
b101110 :
b101110 &
b101110 9
b11100010 8
b11100010 %
b11100010 7
b11111 2
b11111 #
b11111 1
b100 /
#130000
0'
#135000
b1110011 !
b1110011 L
b110011 "
b110011 K
1'
#140000
0'
#145000
1'
#150000
0'
#155000
1'
#160000
0'
#165000
b110 D
b1100111 C
b1000001 B
b110000 6
b1000111 A
b1111111 @
b1000 5
b11000 ?
b11001001 J
b1110101 F
b111000 H
b1110111 M
b11001001 G
b11100 E
b111000 I
1'
b1100001 -
b11110001 ,
b1101001 +
b1110111 <
b1110111 )
b1110111 ;
b100001 >
b100001 *
b100001 =
b11101000 :
b11101000 &
b11101000 9
b11001 8
b11001 %
b11001 7
b1110101 4
b1110101 $
b1110101 3
b11100 2
b11100 #
b11100 1
b101 /
#170000
0'
#175000
b110 !
b110 L
b1100111 "
b1100111 K
1'
#180000
0'
#185000
1'
#190000
0'
#195000
1'
#200000
0'
#205000
b11010011 D
b11011010 C
b10000000 B
b10000001 6
b1010011 A
b11001010 @
b11000 5
b10000 ?
b11011010 J
b10000101 F
b11110001 H
b11010010 M
b11011010 G
b11000 E
b11110001 I
1'
b1001 -
b101011 ,
b10011101 +
b11010010 <
b11010010 )
b11010010 ;
b1000101 >
b1000101 *
b1000101 =
b10011111 :
b10011111 &
b10011111 9
b10110100 8
b10110100 %
b10110100 7
b10000101 4
b10000101 $
b10000101 3
b11000 2
b11000 #
b11000 1
b110 /
#210000
0'
#215000
b11010011 !
b11010011 L
b11011010 "
b11011010 K
1'
#220000
0'
#225000
1'
#230000
0'
#235000
1'
#240000
0'
#245000
b1110100 D
b1111000 C
b10001001 B
b100 6
b11111101 A
b1111000 @
b10000001 5
b0 ?
b11001001 J
b10001111 F
b1000100 H
b11111001 M
b11001001 G
b10010011 E
b1000100 I
1'
b1100 -
b10001101 ,
b11100 +
b11111001 <
b11111001 )
b11111001 ;
b10010011 >
b10010011 *
b10010011 =
b1011010 :
b1011010 &
b1011010 9
b11010111 8
b11010111 %
b11010111 7
b10001111 4
b10001111 $
b10001111 3
b10010011 2
b10010011 #
b10010011 1
b111 /
#250000
0'
#255000
b1110100 !
b1110100 L
b1111000 "
b1111000 K
1'
#260000
0'
#265000
1'
#270000
0'
#275000
1'
#280000
0'
#285000
b1000000 D
b1010010 C
b0 B
b10001 6
b1000000 A
b1010011 @
b10 5
b1 ?
b10000110 J
b10001 F
b10110001 H
b1010001 M
b10000110 G
b1000011 E
b10110001 I
1'
b10010 -
b110111 ,
b1010010 +
b1010001 <
b1010001 )
b1010001 ;
b11110110 >
b11110110 *
b11110110 =
b1110000 :
b1110000 &
b1110000 9
b1000111 8
b1000111 %
b1000111 7
b10001 4
b10001 $
b10001 3
b1000011 2
b1000011 #
b1000011 1
b1000 /
#290000
0'
#295000
b1000000 !
b1000000 L
b1010010 "
b1010010 K
1'
#300000
0'
#305000
1'
#310000
0'
#315000
1'
#320000
0'
#325000
b10001111 D
b10001100 C
b10100 B
b10011011 A
b11011110 @
b1010100 5
b1010010 ?
b1111100 J
b10101 F
b11011011 H
b10001010 M
b1111100 G
b1010110 E
b11011011 I
1'
b11 -
b10100111 ,
b1000011 +
b10001010 <
b10001010 )
b10001010 ;
b1000100 >
b1000100 *
b1000100 =
b111000 :
b111000 &
b111000 9
b10011111 8
b10011111 %
b10011111 7
b10101 4
b10101 $
b10101 3
b1010110 2
b1010110 #
b1010110 1
b1001 /
#330000
0'
#335000
b10001111 !
b10001111 L
b10001100 "
b10001100 K
1'
#340000
0'
#345000
1'
#350000
0'
#355000
1'
#360000
0'
#365000
b1000000 D
b1001000 C
b1000000 B
b100000 6
b0 A
b1111000 @
b1011000 5
b110000 ?
b11011001 J
b1100000 F
b10110111 H
b100000 M
b11011001 G
b1111000 E
b10110111 I
1'
b1000 -
b1101110 ,
b11000 +
b100000 <
b100000 )
b100000 ;
b1001000 >
b1001000 *
b1001000 =
b10010001 :
b10010001 &
b10010001 9
b11111111 8
b11111111 %
b11111111 7
b1100000 4
b1100000 $
b1100000 3
b1111000 2
b1111000 #
b1111000 1
b1010 /
#370000
0'
#375000
b1000000 !
b1000000 L
b1001000 "
b1001000 K
1'
#380000
0'
#385000
1'
#390000
0'
#395000
1'
#400000
0'
#405000
b11101010 D
b11100010 C
b100000 B
b11001010 A
b11100010 @
b1000 5
b0 ?
b10111101 J
b10100101 H
b11101010 M
b10111101 G
b1000 E
b10100101 I
1'
b11000 ,
b1101000 +
b11101010 <
b11101010 )
b11101010 ;
b0 >
b0 *
b0 =
b10111101 :
b10111101 &
b10111101 9
b10100101 8
b10100101 %
b10100101 7
b1000 2
b1000 #
b1000 1
b1011 /
#410000
0'
#415000
b11101010 !
b11101010 L
b11100010 "
b11100010 K
1'
#420000
0'
#425000
1'
#430000
0'
#435000
1'
#440000
0'
#445000
b11111 D
b11 C
b10000011 B
b10010000 6
b10011100 A
b10000111 @
b10001011 5
b10000100 ?
b10001011 J
b10010011 F
b10010100 H
b1100 M
b10001011 G
b10001111 E
b10010100 I
1'
b11100 -
b11111 ,
b11100 +
b1100 <
b1100 )
b1100 ;
b11101101 >
b11101101 *
b11101101 =
b1100110 :
b1100110 &
b1100110 9
b1111001 8
b1111001 %
b1111001 7
b10010011 4
b10010011 $
b10010011 3
b10001111 2
b10001111 #
b10001111 1
b1100 /
#450000
0'
#455000
b11111 !
b11111 L
b11 "
b11 K
1'
#460000
0'
#465000
1'
#470000
0'
#475000
1'
#480000
0'
#485000
b100011 D
b1001 C
b0 B
b110000 6
b100011 A
b10101 @
b110 5
b11100 ?
b110 J
b110000 F
b10111100 H
b10011 M
b110 G
b1011111 E
b10111100 I
1'
b101010 -
b10111010 ,
b1101111 +
b10011 <
b10011 )
b10011 ;
b10100001 >
b10100001 *
b10100001 =
b10100111 :
b10100111 &
b10100111 9
b11101 8
b11101 %
b11101 7
b110000 4
b110000 $
b110000 3
b1011111 2
b1011111 #
b1011111 1
b1101 /
#490000
0'
#495000
b100011 !
b100011 L
b1001 "
b1001 K
1'
#500000
0'
#505000
1'
#510000
0'
#515000
1'
#520000
0'
#525000
b11011011 D
b11010101 C
b10110000 B
b110 6
b1101011 A
b11010101 @
b10111000 5
b0 ?
b10111000 J
b11110111 F
b110 H
b1101101 M
b10111000 G
b11111000 E
b110 I
1'
b1110 -
b10111110 ,
b1111 +
b1101101 <
b1101101 )
b1101101 ;
b101111 >
b101111 *
b101111 =
b10010111 :
b10010111 &
b10010111 9
b101001 8
b101001 %
b101001 7
b11110111 4
b11110111 $
b11110111 3
b11111000 2
b11111000 #
b11111000 1
b1110 /
#530000
0'
#535000
b11011011 !
b11011011 L
b11010101 "
b11010101 K
1'
#540000
0'
#545000
1'
#550000
0'
#555000
1'
#560000
0'
#565000
b10110000 D
b110100 C
b1 B
b10100100 6
b10110001 A
b10100 @
b1 5
b100000 ?
b11001 J
b10100111 F
b11110100 H
b10101 M
b11001 G
b100001 E
b11110100 I
1'
b10000100 -
b11101101 ,
b10000110 +
b10101 <
b10101 )
b10101 ;
b111001 >
b111001 *
b111001 =
b100000 :
b100000 &
b100000 9
b11001101 8
b11001101 %
b11001101 7
b10100111 4
b10100111 $
b10100111 3
b100001 2
b100001 #
b100001 1
b1111 /
#570000
0'
#575000
b10110000 !
b10110000 L
b110100 "
b110100 K
1'
#580000
0'
#585000
1'
#590000
0'
#595000
1'
#600000
0'
#605000
b1110101 D
b1110101 C
b1 6
b1110100 A
b1110101 @
b0 5
b0 ?
b11011 J
b1000001 F
b10001011 H
b1110101 M
b11011 G
b1000000 E
b10001011 I
1'
b0 -
b10010000 ,
b1 +
b1110101 <
b1110101 )
b1110101 ;
b11111110 >
b11111110 *
b11111110 =
b11100101 :
b11100101 &
b11100101 9
b1110101 8
b1110101 %
b1110101 7
b1000001 4
b1000001 $
b1000001 3
b1000000 2
b1000000 #
b1000000 1
b10000 /
#610000
0'
#615000
b1110101 !
b1110101 L
b1110101 "
b1110101 K
1'
#620000
0'
#625000
1'
#630000
0'
#635000
1'
#640000
0'
#645000
b11110101 D
b10110101 C
b10001100 B
b10001100 6
b1111001 A
b1111001 @
b10001100 5
b11001100 ?
b10111100 J
b10001101 F
b11111100 H
b11110101 M
b10111100 G
b11001111 E
b11111100 I
1'
b1000000 -
b1000000 ,
b1000010 +
b11110101 <
b11110101 )
b11110101 ;
b11110100 >
b11110100 *
b11110100 =
b1001000 :
b1001000 &
b1001000 9
b1000 8
b1000 %
b1000 7
b10001101 4
b10001101 $
b10001101 3
b11001111 2
b11001111 #
b11001111 1
b10001 /
#650000
0'
#655000
b11110101 !
b11110101 L
b10110101 "
b10110101 K
1'
#660000
0'
#665000
1'
#670000
0'
#675000
1'
#680000
0'
#685000
b10010111 D
b10010011 C
b0 B
b1010000 6
b10010111 A
b11000111 @
b0 5
b1010100 ?
b10001000 J
b1010011 F
b11011100 H
b11000111 M
b10001000 G
b1010100 E
b11011100 I
1'
b100 -
b1010100 ,
b111 +
b11000111 <
b11000111 )
b11000111 ;
b11111010 >
b11111010 *
b11111010 =
b1110010 :
b1110010 &
b1110010 9
b100110 8
b100110 %
b100110 7
b1010011 4
b1010011 $
b1010011 3
b1010100 2
b1010100 #
b1010100 1
b10010 /
#690000
0'
#695000
b10010111 !
b10010111 L
b10010011 "
b10010011 K
1'
#700000
0'
#705000
1'
#710000
0'
#715000
1'
#720000
0'
#725000
b11111101 D
b11101101 C
b100000 B
b110000 6
b11011101 A
b11101001 @
b100 5
b100 ?
b100100 J
b11110010 F
b110100 H
b11101101 M
b100100 G
b10000101 E
b110100 I
1'
b10000 -
b10000 ,
b1110111 +
b11101101 <
b11101101 )
b11101101 ;
b10001010 >
b10001010 *
b10001010 =
b10101110 :
b10101110 &
b10101110 9
b10111110 8
b10111110 %
b10111110 7
b11110010 4
b11110010 $
b11110010 3
b10000101 2
b10000101 #
b10000101 1
b10011 /
#730000
0'
#735000
b11111101 !
b11111101 L
b11101101 "
b11101101 K
1'
#740000
0'
#745000
1'
#750000
0'
#755000
1'
#760000
0'
#765000
b11100111 D
b11010111 C
b1001 6
b11000111 A
b11001110 @
b0 5
b11001 ?
b10101011 F
b1011001 H
b11001110 M
b11011 E
b1011001 I
1'
b110000 -
b1111101 ,
b10110000 +
b11001110 <
b11001110 )
b11001110 ;
b11001100 >
b11001100 *
b11001100 =
b11101000 :
b11101000 &
b11101000 9
b10010101 8
b10010101 %
b10010101 7
b10101011 4
b10101011 $
b10101011 3
b11011 2
b11011 #
b11011 1
b10100 /
#770000
0'
#775000
b11100111 !
b11100111 L
b11010111 "
b11010111 K
1'
#780000
0'
#785000
1'
#790000
0'
#795000
1'
#800000
0'
#805000
b10 D
b1110010 C
b0 B
b1100 6
b10 A
b10001111 @
b10000001 5
b11111101 ?
b10000001 J
b1100 F
b11111101 H
b1110 M
b10000001 G
b11111101 E
b11111101 I
1'
b1110000 -
b1111100 ,
b11110001 +
b1110 <
b1110 )
b1110 ;
b11110010 >
b11110010 *
b11110010 =
b1110011 :
b1110011 &
b1110011 9
b1111 8
b1111 %
b1111 7
b1100 4
b1100 $
b1100 3
b11111101 2
b11111101 #
b11111101 1
b10101 /
#810000
0'
#815000
b10 !
b10 L
b1110010 "
b1110010 K
1'
#820000
0'
#825000
1'
#830000
0'
#835000
1'
#840000
0'
#845000
b11001111 D
b11100111 C
b11000001 B
b10000001 6
b1110 A
b1100111 @
b11101000 5
b10000000 ?
b11111011 J
b11000001 F
b10010001 H
b10001111 M
b11111011 G
b11101000 E
b10010001 I
1'
b101000 -
b1101010 ,
b101001 +
b10001111 <
b10001111 )
b10001111 ;
b1010 >
b1010 *
b1010 =
b11110001 :
b11110001 &
b11110001 9
b10011011 8
b10011011 %
b10011011 7
b11000001 4
b11000001 $
b11000001 3
b11101000 2
b11101000 #
b11101000 1
b10110 /
#850000
0'
#855000
b11001111 !
b11001111 L
b11100111 "
b11100111 K
1'
#860000
0'
#865000
1'
#870000
0'
#875000
1'
#880000
0'
#885000
b10010011 D
b111011 C
b1011100 B
b10010 6
b11001111 A
b11001 @
b11000100 5
b100010 ?
b11011100 J
b1011110 F
b110011 H
b11011101 M
b11011100 G
b11100110 E
b110011 I
1'
b10101000 -
b11101111 ,
b10111000 +
b11011101 <
b11011101 )
b11011101 ;
b11010000 >
b11010000 *
b11010000 =
b1100 :
b1100 &
b1100 9
b11100011 8
b11100011 %
b11100011 7
b1011110 4
b1011110 $
b1011110 3
b11100110 2
b11100110 #
b11100110 1
b10111 /
#890000
0'
#895000
b10010011 !
b10010011 L
b111011 "
b111011 K
1'
#900000
0'
#905000
1'
#910000
0'
#915000
1'
#920000
0'
#925000
b11010 D
b11011 C
b10100 B
b1010100 6
b1110 A
b11001011 @
b10010001 5
b11010000 ?
b10010101 J
b1010110 F
b11010100 H
b1011010 M
b10010101 G
b11010011 E
b11010100 I
1'
b1 -
b1000001 ,
b10000101 +
b1011010 <
b1011010 )
b1011010 ;
b100 >
b100 *
b100 =
b10010001 :
b10010001 &
b10010001 9
b11010000 8
b11010000 %
b11010000 7
b1010110 4
b1010110 $
b1010110 3
b11010011 2
b11010011 #
b11010011 1
b11000 /
#930000
0'
#935000
b11010 !
b11010 L
b11011 "
b11011 K
1'
#940000
0'
#945000
1'
#950000
0'
#955000
1'
#960000
0'
#965000
b11010001 D
b11000000 C
b0 B
b0 6
b11010001 A
b11001101 @
b11100 5
b1101 ?
b11100 J
b100000 F
b1101 H
b11010001 M
b11100 G
b1111111 E
b1101 I
1'
b10001 -
b10001 ,
b1011111 +
b11010001 <
b11010001 )
b11010001 ;
b1000 >
b1000 *
b1000 =
b10100 :
b10100 &
b10100 9
b101 8
b101 %
b101 7
b100000 4
b100000 $
b100000 3
b1111111 2
b1111111 #
b1111111 1
b11001 /
#970000
0'
#975000
b11010001 !
b11010001 L
b11000000 "
b11000000 K
1'
#980000
0'
#985000
1'
#990000
0'
#995000
1'
#1000000
0'
#1005000
b11010110 D
b11110010 C
b110 6
b11010110 A
b1010000 @
b10000000 5
b10100010 ?
b10001000 J
b110 F
b10100111 H
b11010000 M
b10001000 G
b11100010 E
b10100111 I
1'
b100100 -
b101111 ,
b11100100 +
b11010000 <
b11010000 )
b11010000 ;
b1111001 >
b1111001 *
b1111001 =
b11110001 :
b11110001 &
b11110001 9
b11011110 8
b11011110 %
b11011110 7
b110 4
b110 $
b110 3
b11100010 2
b11100010 #
b11100010 1
b11010 /
#1010000
0'
#1015000
b11010110 !
b11010110 L
b11110010 "
b11110010 K
1'
#1020000
0'
#1025000
1'
#1030000
0'
#1035000
1'
#1040000
0'
#1045000
b10011011 D
b10010001 C
b1000001 B
b1000001 6
b11011010 A
b1010010 @
b11001001 5
b11000011 ?
b11001001 J
b1100001 F
b11000011 H
b10011011 M
b11001001 G
b11111111 E
b11000011 I
1'
b1010 -
b1010 ,
b10011110 +
b10011011 <
b10011011 )
b10011011 ;
b1010010 >
b1010010 *
b1010010 =
b10011011 :
b10011011 &
b10011011 9
b10010001 8
b10010001 %
b10010001 7
b1100001 4
b1100001 $
b1100001 3
b11111111 2
b11111111 #
b11111111 1
b11011 /
#1050000
0'
#1055000
b10011011 !
b10011011 L
b10010001 "
b10010001 K
1'
#1060000
0'
#1065000
1'
#1070000
0'
#1075000
1'
#1080000
0'
#1085000
b11111011 D
b11101000 C
b1000 B
b111001 6
b11110011 A
b11000010 @
b1000 5
b101010 ?
b1001000 J
b111001 F
b10111111 H
b11001010 M
b1001000 G
b101010 E
b10111111 I
1'
b10011 -
b11110111 ,
b10011 +
b11001010 <
b11001010 )
b11001010 ;
b1000101 >
b1000101 *
b1000101 =
b1101 :
b1101 &
b1101 9
b11111010 8
b11111010 %
b11111010 7
b111001 4
b111001 $
b111001 3
b101010 2
b101010 #
b101010 1
b11100 /
#1090000
0'
#1095000
b11111011 !
b11111011 L
b11101000 "
b11101000 K
1'
#1100000
0'
#1105000
1'
#1110000
0'
#1115000
1'
#1120000
0'
#1125000
b111100 D
b10101110 C
b10001 B
b1000 6
b101101 A
b100100 @
b1 5
b10001010 ?
b10001 J
b11001 F
b10001010 H
b100101 M
b10001 G
b11101011 E
b10001010 I
1'
b10010010 -
b10011011 ,
b11110010 +
b100101 <
b100101 )
b100101 ;
b10101010 >
b10101010 *
b10101010 =
b10111011 :
b10111011 &
b10111011 9
b100000 8
b100000 %
b100000 7
b11001 4
b11001 $
b11001 3
b11101011 2
b11101011 #
b11101011 1
b11101 /
#1130000
0'
#1135000
b111100 !
b111100 L
b10101110 "
b10101110 K
1'
#1140000
0'
#1145000
1'
#1150000
0'
#1155000
1'
#1160000
0'
#1165000
b1000100 D
b1011000 C
b100001 B
b101000 6
b1100101 A
b1001000 @
b101 5
b10000 ?
b100111 J
b101001 F
b1111000 H
b1001101 M
b100111 G
b10101 E
b1111000 I
1'
b11100 -
b1011111 ,
b111100 +
b1001101 <
b1001101 )
b1001101 ;
b111101 >
b111101 *
b111101 =
b11010 :
b11010 &
b11010 9
b1000101 8
b1000101 %
b1000101 7
b101001 4
b101001 $
b101001 3
b10101 2
b10101 #
b10101 1
b11110 /
#1170000
0'
#1175000
b1000100 !
b1000100 L
b1011000 "
b1011000 K
1'
#1180000
0'
#1185000
1'
#1190000
0'
#1195000
1'
#1200000
0'
#1205000
b11010101 D
b1000100 C
b11011 B
b10 6
b11001110 A
b100 @
b11001000 5
b1000000 ?
b11011011 J
b11111 F
b1000010 H
b11001100 M
b11011011 G
b11101100 E
b1000010 I
1'
b10010001 -
b10011001 ,
b11110011 +
b11001100 <
b11001100 )
b11001100 ;
b10001 >
b10001 *
b10001 =
b11001010 :
b11001010 &
b11001010 9
b1010011 8
b1010011 %
b1010011 7
b11111 4
b11111 $
b11111 3
b11101100 2
b11101100 #
b11101100 1
b11111 /
#1210000
0'
#1215000
b11010101 !
b11010101 L
b1000100 "
b1000100 K
1'
#1220000
0'
#1225000
1'
#1230000
0'
#1235000
1'
#1240000
0'
#1245000
b10000000 D
b10000000 C
b0 B
b0 6
b10000000 A
b0 @
b10000000 5
b10000000 ?
b10000000 J
b10000 F
b10000101 H
b10000000 M
b10000000 G
b10011010 E
b10000101 I
1'
b0 -
b101 ,
b10001010 +
b10000000 <
b10000000 )
b10000000 ;
b10101011 >
b10101011 *
b10101011 =
b101011 :
b101011 &
b101011 9
b101110 8
b101110 %
b101110 7
b10000 4
b10000 $
b10000 3
b10011010 2
b10011010 #
b10011010 1
b100000 /
#1250000
0'
#1255000
b10000000 !
b10000000 L
b10000000 "
b10000000 K
1'
#1260000
0'
#1265000
1'
#1270000
0'
#1275000
1'
#1280000
0'
#1285000
b10101111 D
b10111111 C
b10 B
b1010010 6
b10101101 A
b11111101 @
b10 5
b1000010 ?
b100010 J
b11010110 F
b1011010 H
b11111111 M
b100010 G
b11000111 E
b1011010 I
1'
b10000 -
b1111000 ,
b10001 +
b11111111 <
b11111111 )
b11111111 ;
b11100011 >
b11100011 *
b11100011 =
b11000001 :
b11000001 &
b11000001 9
b10111001 8
b10111001 %
b10111001 7
b11010110 4
b11010110 $
b11010110 3
b11000111 2
b11000111 #
b11000111 1
b100001 /
#1290000
0'
#1295000
b10101111 !
b10101111 L
b10111111 "
b10111111 K
1'
#1300000
0'
#1305000
1'
#1310000
0'
#1315000
1'
#1320000
0'
#1325000
b1000110 D
b1000010 C
b100 B
b10000000 6
b1000010 A
b11000011 @
b1 5
b10000001 ?
b100101 J
b11001110 F
b10010001 H
b11000010 M
b100101 G
b10001011 E
b10010001 I
1'
b100 -
b10110100 ,
b1000101 +
b11000010 <
b11000010 )
b11000010 ;
b10001001 >
b10001001 *
b10001001 =
b10101100 :
b10101100 &
b10101100 9
b11000 8
b11000 %
b11000 7
b11001110 4
b11001110 $
b11001110 3
b10001011 2
b10001011 #
b10001011 1
b100010 /
#1330000
0'
#1335000
b1000110 !
b1000110 L
b1000010 "
b1000010 K
1'
#1340000
0'
#1345000
1'
#1350000
0'
#1355000
1'
#1360000
0'
