src/Testing/HPC2/Share_1/hpc2.v
module HPC2(
    clk,
    a0,
    a1,
    b0,
    b1,
    rand_01,
    c0,
    c1
);
//INPUTS
    input clk;
    input  [7:0] a0;
    input  [7:0] a1;
    input  [7:0] b0;
    input  [7:0] b1;
    input  [7:0] rand_01;
//OUTPUTS
    output reg  [7:0] c0;
    output reg  [7:0] c1;
//Intermediate values
    wire [7:0] a0_inp;
    wire [7:0] a1_inp;
    wire [7:0] b0_inp;
    wire [7:0] b1_inp;
    wire [7:0] rand_01_inp;
    reg [7:0] b_share_reg_hpc2_same_shares_1_order0;
    reg [7:0] a0_inp_reg;
    wire [7:0] z1_assgn1;
    reg [7:0] u00;
    reg [7:0] temp_hpc2_v_1_order0;
    wire [7:0] z3_assgn3;
    reg [7:0] v01;
    reg [7:0] rand_reg_hpc2_w_1_order0;
    wire [7:0] a_neg_hpc2_w_1_order0;
    reg [7:0] a_neg_hpc2_w_1_order0_reg;
    wire [7:0] z5_assgn5;
    reg [7:0] w01;
    wire [7:0] u01;
    reg [7:0] temp_hpc2_v_1_order1;
    reg [7:0] a1_inp_reg;
    wire [7:0] z7_assgn7;
    reg [7:0] v10;
    reg [7:0] rand_reg_hpc2_w_1_order1;
    wire [7:0] a_neg_hpc2_w_1_order1;
    reg [7:0] a_neg_hpc2_w_1_order1_reg;
    wire [7:0] z9_assgn9;
    reg [7:0] w10;
    wire [7:0] u10;
    reg [7:0] b_share_reg_hpc2_same_shares_1_order1;
    wire [7:0] z11_assgn11;
    reg [7:0] u11;

    assign a0_inp = a0;
    assign a1_inp = a1;
    assign b0_inp = b0;
    assign b1_inp = b1;
    assign rand_01_inp = rand_01;
    assign z1_assgn1 = (a0_inp_reg & b_share_reg_hpc2_same_shares_1_order0);
    assign z3_assgn3 = (temp_hpc2_v_1_order0 & a0_inp_reg);
    assign a_neg_hpc2_w_1_order0 = ~a0_inp;
    assign z5_assgn5 = (a_neg_hpc2_w_1_order0_reg & rand_reg_hpc2_w_1_order0);
    assign u01 = (v01 ^ w01);
    assign z7_assgn7 = (temp_hpc2_v_1_order1 & a1_inp_reg);
    assign a_neg_hpc2_w_1_order1 = ~a1_inp;
    assign z9_assgn9 = (a_neg_hpc2_w_1_order1_reg & rand_reg_hpc2_w_1_order1);
    assign u10 = (v10 ^ w10);
    assign z11_assgn11 = (a1_inp_reg & b_share_reg_hpc2_same_shares_1_order1);

    always @(posedge clk) begin
        b_share_reg_hpc2_same_shares_1_order0 <= b0_inp;
        a0_inp_reg <= a0_inp;
        u00 <= z1_assgn1;
        temp_hpc2_v_1_order0 <= (b1_inp ^ rand_01_inp);
        v01 <= z3_assgn3;
        rand_reg_hpc2_w_1_order0 <= rand_01_inp;
        a_neg_hpc2_w_1_order0_reg <= a_neg_hpc2_w_1_order0;
        w01 <= z5_assgn5;
        temp_hpc2_v_1_order1 <= (b0_inp ^ rand_01_inp);
        a1_inp_reg <= a1_inp;
        v10 <= z7_assgn7;
        rand_reg_hpc2_w_1_order1 <= rand_01_inp;
        a_neg_hpc2_w_1_order1_reg <= a_neg_hpc2_w_1_order1;
        w10 <= z9_assgn9;
        b_share_reg_hpc2_same_shares_1_order1 <= b1_inp;
        u11 <= z11_assgn11;
        c0 <= (u00 ^ u01);
        c1 <= (u10 ^ u11);
    end

endmodule

src/Testing/HPC2/Share_1/hpc2_tb.v
`timescale 1ns/1ps

module HPC2_tb;

    // Signals
    reg clk;
    reg   [7:0] a0, a1;
    reg   [7:0] b0, b1;
    reg   [7:0] rand_01;
    wire  [7:0] c0, c1;

    integer fd, r;
    integer line_num;
    integer exp_a, exp_b, exp_c;
    reg [8*256:0] header; // to skip header line in CSV

    // Instantiate DUT
    HPC2 uut (
        .clk(clk),
        .a0(a0), .a1(a1),
        .b0(b0), .b1(b1),
        .rand_01(rand_01),
        .c0(c0), .c1(c1)
    );

    // Clock
    initial begin
        clk = 0;
        forever #5 clk = ~clk;
    end

    // Stimulus
    initial begin
        // VCD dump
        $dumpfile("hpc2_tb.vcd");
        $dumpvars(0, HPC2_tb);

        // Open CSV file
        fd = $fopen("test_vectors.csv", "r");
        if (fd == 0) begin
            $display("ERROR: Could not open test_vectors.csv");
            $finish;
        end

        // Skip header
        r = $fgets(header, fd);

        line_num = 0;

        // Read lines until EOF
        while (!$feof(fd)) begin
            line_num = line_num + 1;

            r = $fscanf(fd, "%d,%d,%d,%d,%d,%d,%d,%d\n",
                        a0, a1, b0, b1, rand_01,
                        exp_a, exp_b, exp_c);

            @(posedge clk); // wait 1 cycle for DUT to compute
            #30;
            if ((c0 ^ c1) == exp_c)
                $display("Line %0d: PASS (a0=%0d a1=%0d b0=%0d b1=%0d r=%0d) -> c0^c1=%0d expected=%0d",
                         line_num, a0, a1, b0, b1, rand_01, (c0 ^ c1), exp_c);
            else
                $display("Line %0d: FAIL (a0=%0d a1=%0d b0=%0d b1=%0d r=%0d c0=%0d c1=%0d) -> c0^c1=%0d expected=%0d",
                         line_num, a0, a1, b0, b1, rand_01, c0, c1, (c0 ^ c1), exp_c);
        end

        $fclose(fd);
        $display("All test vectors processed.");
        #20 $finish;
    end

endmodule

src/Testing/HPC2/Share_1/hpc2_tb.vcd
$date
	Sat Aug 30 12:44:50 2025
$end
$version
	Icarus Verilog
$end
$timescale
	1ps
$end
$scope module HPC2_tb $end
$var wire 8 ! c1 [7:0] $end
$var wire 8 " c0 [7:0] $end
$var reg 8 # a0 [7:0] $end
$var reg 8 $ a1 [7:0] $end
$var reg 8 % b0 [7:0] $end
$var reg 8 & b1 [7:0] $end
$var reg 1 ' clk $end
$var reg 2049 ( header [2048:0] $end
$var reg 8 ) rand_01 [7:0] $end
$var integer 32 * exp_a [31:0] $end
$var integer 32 + exp_b [31:0] $end
$var integer 32 , exp_c [31:0] $end
$var integer 32 - fd [31:0] $end
$var integer 32 . line_num [31:0] $end
$var integer 32 / r [31:0] $end
$scope module uut $end
$var wire 8 0 a0 [7:0] $end
$var wire 8 1 a0_inp [7:0] $end
$var wire 8 2 a1 [7:0] $end
$var wire 8 3 a1_inp [7:0] $end
$var wire 8 4 a_neg_hpc2_w_1_order0 [7:0] $end
$var wire 8 5 a_neg_hpc2_w_1_order1 [7:0] $end
$var wire 8 6 b0 [7:0] $end
$var wire 8 7 b0_inp [7:0] $end
$var wire 8 8 b1 [7:0] $end
$var wire 8 9 b1_inp [7:0] $end
$var wire 1 ' clk $end
$var wire 8 : rand_01 [7:0] $end
$var wire 8 ; rand_01_inp [7:0] $end
$var wire 8 < u01 [7:0] $end
$var wire 8 = u10 [7:0] $end
$var wire 8 > z11_assgn11 [7:0] $end
$var wire 8 ? z1_assgn1 [7:0] $end
$var wire 8 @ z3_assgn3 [7:0] $end
$var wire 8 A z5_assgn5 [7:0] $end
$var wire 8 B z7_assgn7 [7:0] $end
$var wire 8 C z9_assgn9 [7:0] $end
$var reg 8 D a0_inp_reg [7:0] $end
$var reg 8 E a1_inp_reg [7:0] $end
$var reg 8 F a_neg_hpc2_w_1_order0_reg [7:0] $end
$var reg 8 G a_neg_hpc2_w_1_order1_reg [7:0] $end
$var reg 8 H b_share_reg_hpc2_same_shares_1_order0 [7:0] $end
$var reg 8 I b_share_reg_hpc2_same_shares_1_order1 [7:0] $end
$var reg 8 J c0 [7:0] $end
$var reg 8 K c1 [7:0] $end
$var reg 8 L rand_reg_hpc2_w_1_order0 [7:0] $end
$var reg 8 M rand_reg_hpc2_w_1_order1 [7:0] $end
$var reg 8 N temp_hpc2_v_1_order0 [7:0] $end
$var reg 8 O temp_hpc2_v_1_order1 [7:0] $end
$var reg 8 P u00 [7:0] $end
$var reg 8 Q u11 [7:0] $end
$var reg 8 R v01 [7:0] $end
$var reg 8 S v10 [7:0] $end
$var reg 8 T w01 [7:0] $end
$var reg 8 U w10 [7:0] $end
$upscope $end
$upscope $end
$enddefinitions $end
$comment Show the parameter values. $end
$dumpall
$end
#0
$dumpvars
bx U
bx T
bx S
bx R
bx Q
bx P
bx O
bx N
bx M
bx L
bx K
bx J
bx I
bx H
bx G
bx F
bx E
bx D
bx C
bx B
bx A
bx @
bx ?
bx >
bx =
bx <
b11111 ;
b11111 :
b1110010 9
b1110010 8
b1011010 7
b1011010 6
b11110011 5
b10100000 4
b1100 3
b1100 2
b1011111 1
b1011111 0
b1000 /
b1 .
b10000000000000000000000000000011 -
b0 ,
b101000 +
b1010011 *
b11111 )
b110000100110000001011000110000100110001001011000110001000110000001011000110001000110001001011000111001001100001011011100110010001011111001100000011000100101100011000010010110001100010001011000110001100001010 (
0'
b1110010 &
b1011010 %
b1100 $
b1011111 #
bx "
bx !
$end
#5000
b10011 C
b0 >
b100 B
b0 A
b1001101 @
b1011010 ?
b1110010 I
b11110011 G
b11111 M
b1100 E
b1000101 O
b10100000 F
b11111 L
b1101101 N
b1011111 D
b1011010 H
1'
#10000
0'
#15000
b10111 =
b1001101 <
b0 Q
b10011 U
b100 S
b0 T
b1001101 R
b1011010 P
1'
#20000
0'
#25000
b10111 !
b10111 K
b10111 "
b10111 J
1'
#30000
0'
#35000
b10000 C
b1001 >
b1100 B
b1000100 @
b10 ?
b11011001 I
b11110010 G
b10100 M
b1101 E
b111110 O
b10101001 F
b10100 L
b11001101 N
b1010110 D
b101010 H
b11110010 5
b10101001 4
1'
b1010011 ,
b11110011 +
b1011011 *
b10100 ;
b10100 )
b10100 :
b11011001 9
b11011001 &
b11011001 8
b101010 7
b101010 %
b101010 6
b1101 3
b1101 $
b1101 2
b1010110 1
b1010110 #
b1010110 0
b10 .
#40000
0'
#45000
b11100 =
b1000100 <
b1001 Q
b10000 U
b1100 S
b1000100 R
b10 P
1'
#50000
0'
#55000
b10101 !
b10101 K
b1000110 "
b1000110 J
1'
#60000
0'
#65000
b10000000 C
b10001 >
b1010010 B
b10010000 A
b100010 @
b1100101 ?
b10010001 I
b10001100 G
b10110011 M
b1110011 E
b11011110 O
b10011000 F
b10110011 L
b100010 N
b1100111 D
b1101101 H
b10001100 5
b10011000 4
1'
b10100 ,
b11111100 +
b10100 *
b10110011 ;
b10110011 )
b10110011 :
b10010001 9
b10010001 &
b10010001 8
b1101101 7
b1101101 %
b1101101 6
b1110011 3
b1110011 $
b1110011 2
b1100111 1
b1100111 #
b1100111 0
b11 .
#70000
0'
#75000
b11010010 =
b10110010 <
b10001 Q
b10000000 U
b1010010 S
b10010000 T
b100010 R
b1100101 P
1'
#80000
0'
#85000
b11000011 !
b11000011 K
b11010111 "
b11010111 J
1'
#90000
0'
#95000
b11001001 C
b10 >
b10010 B
b11101011 A
b10000 @
b0 ?
b11001110 I
b11001101 G
b11111011 M
b110010 E
b10011110 O
b11101111 F
b11111011 L
b110101 N
b10000 D
b1100101 H
b11001101 5
b11101111 4
1'
b100010 ,
b10101011 +
b100010 *
b11111011 ;
b11111011 )
b11111011 :
b11001110 9
b11001110 &
b11001110 8
b1100101 7
b1100101 %
b1100101 6
b110010 3
b110010 $
b110010 2
b10000 1
b10000 #
b10000 0
b100 .
#100000
0'
#105000
b11011011 =
b11111011 <
b10 Q
b11001001 U
b10010 S
b11101011 T
b10000 R
b0 P
1'
#110000
0'
#115000
b11011001 !
b11011001 K
b11111011 "
b11111011 J
1'
#120000
0'
#125000
b1110000 C
b0 >
b0 B
b0 A
b100000 @
b1010010 I
b11111111 G
b1110000 M
b0 E
b1111010 O
b1110 F
b1110000 L
b100010 N
b11110001 D
b1010 H
b11111111 5
b1110 4
1'
b1010000 ,
b1011000 +
b11110001 *
b1110000 ;
b1110000 )
b1110000 :
b1010010 9
b1010010 &
b1010010 8
b1010 7
b1010 %
b1010 6
b0 3
b0 $
b0 2
b11110001 1
b11110001 #
b11110001 0
b101 .
#130000
0'
#135000
b1110000 =
b100000 <
b0 Q
b1110000 U
b0 S
b0 T
b100000 R
1'
#140000
0'
#145000
b1110000 !
b1110000 K
b100000 "
b100000 J
1'
#150000
0'
#155000
b1010100 C
b1001 >
b100001 B
b1101 A
b110000 @
b1001001 I
b1010100 G
b1111101 M
b10101011 E
b1110101 O
b10001111 F
b1111101 L
b110100 N
b1110000 D
b1000 H
b1010100 5
b10001111 4
1'
b1000001 ,
b1000001 +
b11011011 *
b1111101 ;
b1111101 )
b1111101 :
b1001001 9
b1001001 &
b1001001 8
b1000 7
b1000 %
b1000 6
b10101011 3
b10101011 $
b10101011 2
b1110000 1
b1110000 #
b1110000 0
b110 .
#160000
0'
#165000
b1110101 =
b111101 <
b1001 Q
b1010100 U
b100001 S
b1101 T
b110000 R
1'
#170000
0'
#175000
b1111100 !
b1111100 K
b111101 "
b111101 J
1'
#180000
0'
#185000
b10010 C
b10001000 >
b10000000 B
b1011 A
b10100 @
b10001110 I
b1010110 G
b11011 M
b10101001 E
b10010010 O
b11001011 F
b11011 L
b10010101 N
b110100 D
b10001001 H
b1010110 5
b11001011 4
1'
b101 ,
b111 +
b10011101 *
b11011 ;
b11011 )
b11011 :
b10001110 9
b10001110 &
b10001110 8
b10001001 7
b10001001 %
b10001001 6
b10101001 3
b10101001 $
b10101001 2
b110100 1
b110100 #
b110100 0
b111 .
#190000
0'
#195000
b10010010 =
b11111 <
b10001000 Q
b10010 U
b10000000 S
b1011 T
b10100 R
1'
#200000
0'
#205000
b11010 !
b11010 K
b11111 "
b11111 J
1'
#210000
0'
#215000
b11010 C
b11000001 >
b10000100 B
b10110 A
b101001 @
b101000 ?
b11010011 I
b11010 G
b10111110 M
b11100101 E
b10010110 O
b1010110 F
b10111110 L
b1101101 N
b10101001 D
b101000 H
b11010 5
b1010110 4
1'
b1001000 ,
b11111011 +
b1001100 *
b10111110 ;
b10111110 )
b10111110 :
b11010011 9
b11010011 &
b11010011 8
b101000 7
b101000 %
b101000 6
b11100101 3
b11100101 $
b11100101 2
b10101001 1
b10101001 #
b10101001 0
b1000 .
#220000
0'
#225000
b10011110 =
b111111 <
b11000001 Q
b11010 U
b10000100 S
b10110 T
b101001 R
b101000 P
1'
#230000
0'
#235000
b1011111 !
b1011111 K
b10111 "
b10111 J
1'
#240000
0'
#245000
b11000100 C
b101010 >
b111001 B
b11000000 A
b100100 @
b110000 ?
b10101010 I
b11000100 G
b11001100 M
b111011 E
b11111101 O
b11000011 F
b11001100 L
b1100110 N
b111100 D
b110001 H
b11000100 5
b11000011 4
1'
b11 ,
b10011011 +
b111 *
b11001100 ;
b11001100 )
b11001100 :
b10101010 9
b10101010 &
b10101010 8
b110001 7
b110001 %
b110001 6
b111011 3
b111011 $
b111011 2
b111100 1
b111100 #
b111100 0
b1001 .
#250000
0'
#255000
b11111101 =
b11100100 <
b101010 Q
b11000100 U
b111001 S
b11000000 T
b100100 R
b110000 P
1'
#260000
0'
#265000
b11010111 !
b11010111 K
b11010100 "
b11010100 J
1'
#270000
0'
#275000
b1 C
b1010 >
b110010 B
b1000 A
b11000001 @
b11100100 ?
b1001010 I
b1000101 G
b10001001 M
b10111010 E
b1110111 O
b11010 F
b10001001 L
b11000011 N
b11100101 D
b11111110 H
b1000101 5
b11010 4
1'
b10100 ,
b10110100 +
b1011111 *
b10001001 ;
b10001001 )
b10001001 :
b1001010 9
b1001010 &
b1001010 8
b11111110 7
b11111110 %
b11111110 6
b10111010 3
b10111010 $
b10111010 2
b11100101 1
b11100101 #
b11100101 0
b1010 .
#280000
0'
#285000
b110011 =
b11001001 <
b1010 Q
b1 U
b110010 S
b1000 T
b11000001 R
b11100100 P
1'
#290000
0'
#295000
b111001 !
b111001 K
b101101 "
b101101 J
1'
#300000
0'
#305000
b10000010 C
b100 >
b100 B
b100 A
b10001010 @
b10001000 ?
b100 I
b11000011 G
b10001110 M
b111100 E
b111 O
b101 F
b10001110 L
b10001010 N
b11111010 D
b10001001 H
b11000011 5
b101 4
1'
b10000100 ,
b10001101 +
b11000110 *
b10001110 ;
b10001110 )
b10001110 :
b100 9
b100 &
b100 8
b10001001 7
b10001001 %
b10001001 6
b111100 3
b111100 $
b111100 2
b11111010 1
b11111010 #
b11111010 0
b1011 .
#310000
0'
#315000
b10000110 =
b10001110 <
b100 Q
b10000010 U
b100 S
b100 T
b10001010 R
b10001000 P
1'
#320000
0'
#325000
b10000010 !
b10000010 K
b110 "
b110 J
1'
#330000
0'
#335000
b10001010 C
b0 >
b110 A
b10111001 @
b111000 ?
b1 I
b10001011 G
b10111110 M
b1110100 E
b10000100 O
b110 F
b10111110 L
b10111111 N
b11111001 D
b111010 H
b10001011 5
b110 4
1'
b1001 ,
b111011 +
b10001101 *
b10111110 ;
b10111110 )
b10111110 :
b1 9
b1 &
b1 8
b111010 7
b111010 %
b111010 6
b1110100 3
b1110100 $
b1110100 2
b11111001 1
b11111001 #
b11111001 0
b1100 .
#340000
0'
#345000
b10001110 =
b10111111 <
b0 Q
b10001010 U
b110 T
b10111001 R
b111000 P
1'
#350000
0'
#355000
b10001110 !
b10001110 K
b10000111 "
b10000111 J
1'
#360000
0'
#365000
b11000000 C
b100010 B
b1000000 A
b10000101 @
b100111 ?
b1000001 I
b11001001 G
b11000100 M
b110110 E
b10100011 O
b1001000 F
b11000100 L
b10000101 N
b10110111 D
b1100111 H
b11001001 5
b1001000 4
1'
b0 ,
b100110 +
b10000001 *
b11000100 ;
b11000100 )
b11000100 :
b1000001 9
b1000001 &
b1000001 8
b1100111 7
b1100111 %
b1100111 6
b110110 3
b110110 $
b110110 2
b10110111 1
b10110111 #
b10110111 0
b1101 .
#370000
0'
#375000
b11100010 =
b11000101 <
b11000000 U
b100010 S
b1000000 T
b10000101 R
b100111 P
1'
#380000
0'
#385000
b11100010 !
b11100010 K
b11100010 "
b11100010 J
1'
#390000
0'
#395000
b10101 C
b10101010 >
b0 B
b111101 A
b10 @
b10000000 ?
b10101010 I
b10101 G
b10111101 M
b11101010 E
b10100 O
b1111101 F
b10111101 L
b10111 N
b10000010 D
b10101001 H
b10101 5
b1111101 4
1'
b11 +
b1101000 *
b10111101 ;
b10111101 )
b10111101 :
b10101010 9
b10101010 &
b10101010 8
b10101001 7
b10101001 %
b10101001 6
b11101010 3
b11101010 $
b11101010 2
b10000010 1
b10000010 #
b10000010 0
b1110 .
#400000
0'
#405000
b10101 =
b111111 <
b10101010 Q
b10101 U
b0 S
b111101 T
b10 R
b10000000 P
1'
#410000
0'
#415000
b10111111 !
b10111111 K
b10111111 "
b10111111 J
1'
#420000
0'
#425000
b10000 C
b10000001 >
b1100001 B
b10010000 A
b0 @
b1100000 ?
b10011001 I
b11000 G
b10010001 M
b11100111 E
b1101001 O
b10011000 F
b10010001 L
b1000 N
b1100111 D
b11111000 H
b11000 5
b10011000 4
1'
b1100001 +
b10000000 *
b10010001 ;
b10010001 )
b10010001 :
b10011001 9
b10011001 &
b10011001 8
b11111000 7
b11111000 %
b11111000 6
b11100111 3
b11100111 $
b11100111 2
b1100111 1
b1100111 #
b1100111 0
b1111 .
#430000
0'
#435000
b1110001 =
b10010000 <
b10000001 Q
b10000 U
b1100001 S
b10010000 T
b0 R
b1100000 P
1'
#440000
0'
#445000
b11110000 !
b11110000 K
b11110000 "
b11110000 J
1'
#450000
0'
#455000
b10000000 C
b1000010 >
b10 B
b1000 A
b1 @
b1000001 ?
b11000011 I
b10000001 G
b11001000 M
b1111110 E
b10000011 O
b111010 F
b11001000 L
b1011 N
b11000101 D
b1001011 H
b10000001 5
b111010 4
1'
b10001000 ,
b10001000 +
b10111011 *
b11001000 ;
b11001000 )
b11001000 :
b11000011 9
b11000011 &
b11000011 8
b1001011 7
b1001011 %
b1001011 6
b1111110 3
b1111110 $
b1111110 2
b11000101 1
b11000101 #
b11000101 0
b10000 .
#460000
0'
#465000
b10000010 =
b1001 <
b1000010 Q
b10000000 U
b10 S
b1000 T
b1 R
b1000001 P
1'
#470000
0'
#475000
b11000000 !
b11000000 K
b1001000 "
b1001000 J
1'
#480000
0'
#485000
b1000010 C
b11100 >
b10000100 B
b10 A
b10010100 @
b100 ?
b1011110 I
b1000010 G
b11000010 M
b10111101 E
b11000110 O
b101011 F
b11000010 L
b10011100 N
b11010100 D
b100 H
b1000010 5
b101011 4
1'
b1001000 ,
b1011010 +
b1101001 *
b11000010 ;
b11000010 )
b11000010 :
b1011110 9
b1011110 &
b1011110 8
b100 7
b100 %
b100 6
b10111101 3
b10111101 $
b10111101 2
b11010100 1
b11010100 #
b11010100 0
b10001 .
#490000
0'
#495000
b11000110 =
b10010110 <
b11100 Q
b1000010 U
b10000100 S
b10 T
b10010100 R
b100 P
1'
#500000
0'
#505000
b11011010 !
b11011010 K
b10010010 "
b10010010 J
1'
#510000
0'
#515000
b1000 C
b1000101 >
b1000111 B
b1001000 A
b10010000 @
b10010 ?
b11001101 I
b10101000 G
b1011001 M
b1010111 E
b1101111 O
b1101100 F
b1011001 L
b10010100 N
b10010011 D
b110110 H
b10101000 5
b1101100 4
1'
b11000000 ,
b11111011 +
b11000100 *
b1011001 ;
b1011001 )
b1011001 :
b11001101 9
b11001101 &
b11001101 8
b110110 7
b110110 %
b110110 6
b1010111 3
b1010111 $
b1010111 2
b10010011 1
b10010011 #
b10010011 0
b10010 .
#520000
0'
#525000
b1001111 =
b11011000 <
b1000101 Q
b1000 U
b1000111 S
b1001000 T
b10010000 R
b10010 P
1'
#530000
0'
#535000
b1010 !
b1010 K
b11001010 "
b11001010 J
1'
#540000
0'
#545000
b1000001 C
b0 >
b0 B
b1 A
b10010100 @
b10000100 ?
b1011011 I
b1111011 G
b11000101 M
b10000100 E
b1001010 O
b1011 F
b11000101 L
b10011110 N
b11110100 D
b10001111 H
b1111011 5
b1011 4
1'
b1010000 ,
b11010100 +
b1110000 *
b11000101 ;
b11000101 )
b11000101 :
b1011011 9
b1011011 &
b1011011 8
b10001111 7
b10001111 %
b10001111 6
b10000100 3
b10000100 $
b10000100 2
b11110100 1
b11110100 #
b11110100 0
b10011 .
#550000
0'
#555000
b1000001 =
b10010101 <
b0 Q
b1000001 U
b0 S
b1 T
b10010100 R
b10000100 P
1'
#560000
0'
#565000
b1000001 !
b1000001 K
b10001 "
b10001 J
1'
#570000
0'
#575000
b0 C
b11011101 >
b101 B
b10001000 A
b1010001 @
b11 ?
b11111101 I
b100010 G
b10001000 M
b11011101 E
b100111 O
b10101100 F
b10001000 L
b1110101 N
b1010011 D
b10101111 H
b100010 5
b10101100 4
1'
b10 ,
b1010010 +
b10001110 *
b10001000 ;
b10001000 )
b10001000 :
b11111101 9
b11111101 &
b11111101 8
b10101111 7
b10101111 %
b10101111 6
b11011101 3
b11011101 $
b11011101 2
b1010011 1
b1010011 #
b1010011 0
b10100 .
#580000
0'
#585000
b101 =
b11011001 <
b11011101 Q
b0 U
b101 S
b10001000 T
b1010001 R
b11 P
1'
#590000
0'
#595000
b11011000 !
b11011000 K
b11011010 "
b11011010 J
1'
#600000
0'
#605000
b10011001 C
b1100100 >
b0 B
b10010000 A
b1000 @
b1101101 ?
b1100101 I
b10011011 G
b11111101 M
b1100100 E
b10010010 O
b10010010 F
b11111101 L
b10011000 N
b1101101 D
b1101111 H
b10011011 5
b10010010 4
1'
b1000 ,
b1010 +
b1001 *
b11111101 ;
b11111101 )
b11111101 :
b1100101 9
b1100101 &
b1100101 8
b1101111 7
b1101111 %
b1101111 6
b1100100 3
b1100100 $
b1100100 2
b1101101 1
b1101101 #
b1101101 0
b10101 .
#610000
0'
#615000
b10011001 =
b10011000 <
b1100100 Q
b10011001 U
b0 S
b10010000 T
b1000 R
b1101101 P
1'
#620000
0'
#625000
b11111101 !
b11111101 K
b11110101 "
b11110101 J
1'
#630000
0'
#635000
b11000100 C
b1010 >
b11101110 A
b0 @
b0 ?
b1001011 I
b11010101 G
b11101110 M
b101010 E
b10010101 O
b11111111 F
b11101110 L
b10100101 N
b0 D
b1111011 H
b11010101 5
b11111111 4
1'
b100000 ,
b110000 +
b101010 *
b11101110 ;
b11101110 )
b11101110 :
b1001011 9
b1001011 &
b1001011 8
b1111011 7
b1111011 %
b1111011 6
b101010 3
b101010 $
b101010 2
b0 1
b0 #
b0 0
b10110 .
#640000
0'
#645000
b11000100 =
b11101110 <
b1010 Q
b11000100 U
b11101110 T
b0 R
b0 P
1'
#650000
0'
#655000
b11001110 !
b11001110 K
b11101110 "
b11101110 J
1'
#660000
0'
#665000
b1011110 C
b0 >
b111010 A
b100 @
b1001000 I
b11011111 G
b1111110 M
b100000 E
b11010101 O
b10111011 F
b1111110 L
b110110 N
b1000100 D
b10101011 H
b11011111 5
b10111011 4
1'
b1100000 ,
b11100011 +
b1100100 *
b1111110 ;
b1111110 )
b1111110 :
b1001000 9
b1001000 &
b1001000 8
b10101011 7
b10101011 %
b10101011 6
b100000 3
b100000 $
b100000 2
b1000100 1
b1000100 #
b1000100 0
b10111 .
#670000
0'
#675000
b1011110 =
b111110 <
b0 Q
b1011110 U
b111010 T
b100 R
1'
#680000
0'
#685000
b1011110 !
b1011110 K
b111110 "
b111110 J
1'
#690000
0'
#695000
b100000 C
b10000000 >
b1011001 B
b10000000 A
b1100 @
b1000101 ?
b10100100 I
b100100 G
b10101000 M
b11011011 E
b1111101 O
b10010010 F
b10101000 L
b1100 N
b1101101 D
b11010101 H
b100100 5
b10010010 4
1'
b110000 ,
b1110001 +
b10110110 *
b10101000 ;
b10101000 )
b10101000 :
b10100100 9
b10100100 &
b10100100 8
b11010101 7
b11010101 %
b11010101 6
b11011011 3
b11011011 $
b11011011 2
b1101101 1
b1101101 #
b1101101 0
b11000 .
#700000
0'
#705000
b1111001 =
b10001100 <
b10000000 Q
b100000 U
b1011001 S
b10000000 T
b1100 R
b1000101 P
1'
#710000
0'
#715000
b11111001 !
b11111001 K
b11001001 "
b11001001 J
1'
#720000
0'
#725000
b1100100 C
b10011000 >
b10011000 B
b11010000 A
b1000 @
b101100 ?
b10111101 I
b1100111 G
b11110100 M
b10011000 E
b11011001 O
b11010001 F
b11110100 L
b1001001 N
b101110 D
b101101 H
b1100111 5
b11010001 4
1'
b10010000 ,
b10010000 +
b11110100 ;
b11110100 )
b11110100 :
b10111101 9
b10111101 &
b10111101 8
b101101 7
b101101 %
b101101 6
b10011000 3
b10011000 $
b10011000 2
b101110 1
b101110 #
b101110 0
b11001 .
#730000
0'
#735000
b11111100 =
b11011000 <
b10011000 Q
b1100100 U
b10011000 S
b11010000 T
b1000 R
b101100 P
1'
#740000
0'
#745000
b1100100 !
b1100100 K
b11110100 "
b11110100 J
1'
#750000
0'
#755000
b1110 C
b0 >
b10001 B
b1100 A
b10100000 @
b11010000 ?
b10100010 I
b11101110 G
b1110 M
b10001 E
b11011111 O
b1101 F
b1110 L
b10101100 N
b11110010 D
b11010001 H
b11101110 5
b1101 4
1'
b1100011 ,
b1110011 +
b11100011 *
b1110 ;
b1110 )
b1110 :
b10100010 9
b10100010 &
b10100010 8
b11010001 7
b11010001 %
b11010001 6
b10001 3
b10001 $
b10001 2
b11110010 1
b11110010 #
b11110010 0
b11010 .
#760000
0'
#765000
b11111 =
b10101100 <
b0 Q
b1110 U
b10001 S
b1100 T
b10100000 R
b11010000 P
1'
#770000
0'
#775000
b11111 !
b11111 K
b1111100 "
b1111100 J
1'
#780000
0'
#785000
b1110000 C
b1000 >
b110 B
b100100 A
b11000 @
b1010000 ?
b11001000 I
b11110000 G
b1110100 M
b1111 E
b110 O
b10100110 F
b1110100 L
b10111100 N
b1011001 D
b1110010 H
b11110000 5
b10100110 4
1'
b10010 ,
b10111010 +
b1010110 *
b1110100 ;
b1110100 )
b1110100 :
b11001000 9
b11001000 &
b11001000 8
b1110010 7
b1110010 %
b1110010 6
b1111 3
b1111 $
b1111 2
b1011001 1
b1011001 #
b1011001 0
b11011 .
#790000
0'
#795000
b1110110 =
b111100 <
b1000 Q
b1110000 U
b110 S
b100100 T
b11000 R
b1010000 P
1'
#800000
0'
#805000
b1111110 !
b1111110 K
b1101100 "
b1101100 J
1'
#810000
0'
#815000
b10100 C
b11001000 >
b10001000 B
b100 A
b1110000 @
b10000 ?
b11101011 I
b110111 G
b10100 M
b11001000 E
b10001011 O
b10001111 F
b10100 L
b11111111 N
b1110000 D
b10011111 H
b110111 5
b10001111 4
1'
b110000 ,
b1110100 +
b10111000 *
b10100 ;
b10100 )
b10100 :
b11101011 9
b11101011 &
b11101011 8
b10011111 7
b10011111 %
b10011111 6
b11001000 3
b11001000 $
b11001000 2
b1110000 1
b1110000 #
b1110000 0
b11100 .
#820000
0'
#825000
b10011100 =
b1110100 <
b11001000 Q
b10100 U
b10001000 S
b100 T
b1110000 R
b10000 P
1'
#830000
0'
#835000
b1010100 !
b1010100 K
b1100100 "
b1100100 J
1'
#840000
0'
#845000
b1010000 C
b101000 >
b1100 B
b1110000 A
b0 @
b100 ?
b111000 I
b11010000 G
b1111000 M
b101111 E
b1001100 O
b1110010 F
b1111000 L
b1000000 N
b10001101 D
b110100 H
b11010000 5
b1110010 4
1'
b0 ,
b1100 +
b10100010 *
b1111000 ;
b1111000 )
b1111000 :
b111000 9
b111000 &
b111000 8
b110100 7
b110100 %
b110100 6
b101111 3
b101111 $
b101111 2
b10001101 1
b10001101 #
b10001101 0
b11101 .
#850000
0'
#855000
b1011100 =
b1110000 <
b101000 Q
b1010000 U
b1100 S
b1110000 T
b0 R
b100 P
1'
#860000
0'
#865000
b1110100 !
b1110100 K
b1110100 "
b1110100 J
1'
#870000
0'
