src/Testing/HPC2/Share_1/hpc2.v
module HPC2(
    clk,
    a0,
    a1,
    b0,
    b1,
    rand_01,
    c0,
    c1
);
//INPUTS
    input clk;
    input  [7:0] a0;
    input  [7:0] a1;
    input  [7:0] b0;
    input  [7:0] b1;
    input  [7:0] rand_01;
//OUTPUTS
    output reg  [7:0] c0;
    output reg  [7:0] c1;
//Intermediate values
    wire [7:0] a0_inp;
    wire [7:0] a1_inp;
    wire [7:0] b0_inp;
    wire [7:0] b1_inp;
    wire [7:0] rand_01_inp;
    reg [7:0] b_share_reg_hpc2_same_shares_1_order0;
    reg [7:0] a0_inp_reg;
    wire [7:0] z1_assgn1;
    reg [7:0] u00;
    reg [7:0] temp_hpc2_v_1_order0;
    wire [7:0] z3_assgn3;
    reg [7:0] v01;
    reg [7:0] rand_reg_hpc2_w_1_order0;
    wire [7:0] a_neg_hpc2_w_1_order0;
    reg [7:0] a_neg_hpc2_w_1_order0_reg;
    wire [7:0] z5_assgn5;
    reg [7:0] w01;
    wire [7:0] u01;
    reg [7:0] temp_hpc2_v_1_order1;
    reg [7:0] a1_inp_reg;
    wire [7:0] z7_assgn7;
    reg [7:0] v10;
    reg [7:0] rand_reg_hpc2_w_1_order1;
    wire [7:0] a_neg_hpc2_w_1_order1;
    reg [7:0] a_neg_hpc2_w_1_order1_reg;
    wire [7:0] z9_assgn9;
    reg [7:0] w10;
    wire [7:0] u10;
    reg [7:0] b_share_reg_hpc2_same_shares_1_order1;
    wire [7:0] z11_assgn11;
    reg [7:0] u11;

    assign a0_inp = a0;
    assign a1_inp = a1;
    assign b0_inp = b0;
    assign b1_inp = b1;
    assign rand_01_inp = rand_01;
    assign z1_assgn1 = (a0_inp_reg & b_share_reg_hpc2_same_shares_1_order0);
    assign z3_assgn3 = (temp_hpc2_v_1_order0 & a0_inp_reg);
    assign a_neg_hpc2_w_1_order0 = ~a0_inp;
    assign z5_assgn5 = (a_neg_hpc2_w_1_order0_reg & rand_reg_hpc2_w_1_order0);
    assign u01 = (v01 ^ w01);
    assign z7_assgn7 = (temp_hpc2_v_1_order1 & a1_inp_reg);
    assign a_neg_hpc2_w_1_order1 = ~a1_inp;
    assign z9_assgn9 = (a_neg_hpc2_w_1_order1_reg & rand_reg_hpc2_w_1_order1);
    assign u10 = (v10 ^ w10);
    assign z11_assgn11 = (a1_inp_reg & b_share_reg_hpc2_same_shares_1_order1);

    always @(posedge clk) begin
        b_share_reg_hpc2_same_shares_1_order0 <= b0_inp;
        a0_inp_reg <= a0_inp;
        u00 <= z1_assgn1;
        temp_hpc2_v_1_order0 <= (b1_inp ^ rand_01_inp);
        v01 <= z3_assgn3;
        rand_reg_hpc2_w_1_order0 <= rand_01_inp;
        a_neg_hpc2_w_1_order0_reg <= a_neg_hpc2_w_1_order0;
        w01 <= z5_assgn5;
        temp_hpc2_v_1_order1 <= (b0_inp ^ rand_01_inp);
        a1_inp_reg <= a1_inp;
        v10 <= z7_assgn7;
        rand_reg_hpc2_w_1_order1 <= rand_01_inp;
        a_neg_hpc2_w_1_order1_reg <= a_neg_hpc2_w_1_order1;
        w10 <= z9_assgn9;
        b_share_reg_hpc2_same_shares_1_order1 <= b1_inp;
        u11 <= z11_assgn11;
        c0 <= (u00 ^ u01);
        c1 <= (u10 ^ u11);
    end

endmodule

src/Testing/HPC2/Share_1/hpc2_tb.v
`timescale 1ns/1ps

module HPC2_tb;

    // Signals
    reg clk;
    reg   [7:0] a0, a1;
    reg   [7:0] b0, b1;
    reg   [7:0] rand_01;
    wire  [7:0] c0, c1;

    integer fd, r;
    integer line_num;
    integer exp_a, exp_b, exp_c;
    reg [8*256:0] header; // to skip header line in CSV

    // Instantiate DUT
    HPC2 uut (
        .clk(clk),
        .a0(a0), .a1(a1),
        .b0(b0), .b1(b1),
        .rand_01(rand_01),
        .c0(c0), .c1(c1)
    );

    // Clock
    initial begin
        clk = 0;
        forever #5 clk = ~clk;
    end

    // Stimulus
    initial begin
        // VCD dump
        $dumpfile("hpc2_tb.vcd");
        $dumpvars(0, HPC2_tb);

        // Open CSV file
        fd = $fopen("test_vectors.csv", "r");
        if (fd == 0) begin
            $display("ERROR: Could not open test_vectors.csv");
            $finish;
        end

        // Skip header
        r = $fgets(header, fd);

        line_num = 0;

        // Read lines until EOF
        while (!$feof(fd)) begin
            line_num = line_num + 1;

            r = $fscanf(fd, "%d,%d,%d,%d,%d,%d,%d,%d\n",
                        a0, a1, b0, b1, rand_01,
                        exp_a, exp_b, exp_c);

            @(posedge clk); // wait 1 cycle for DUT to compute
            #30;
            if ((c0 ^ c1) == exp_c)
                $display("Line %0d: PASS (a0=%0d a1=%0d b0=%0d b1=%0d r=%0d) -> c0^c1=%0d expected=%0d",
                         line_num, a0, a1, b0, b1, rand_01, (c0 ^ c1), exp_c);
            else
                $display("Line %0d: FAIL (a0=%0d a1=%0d b0=%0d b1=%0d r=%0d c0=%0d c1=%0d) -> c0^c1=%0d expected=%0d",
                         line_num, a0, a1, b0, b1, rand_01, c0, c1, (c0 ^ c1), exp_c);
        end

        $fclose(fd);
        $display("All test vectors processed.");
        #20 $finish;
    end

endmodule

src/Testing/HPC2/Share_1/HPC2_tb.vcd
$date
	Sat Aug 23 13:17:53 2025
$end
$version
	Icarus Verilog
$end
$timescale
	1ps
$end
$scope module HPC2_tb $end
$var wire 8 ! c1 [7:0] $end
$var wire 8 " c0 [7:0] $end
$var reg 8 # a0 [7:0] $end
$var reg 8 $ a1 [7:0] $end
$var reg 8 % b0 [7:0] $end
$var reg 8 & b1 [7:0] $end
$var reg 1 ' clk $end
$var reg 2049 ( header [2048:0] $end
$var reg 8 ) rand_01 [7:0] $end
$var integer 32 * exp_a [31:0] $end
$var integer 32 + exp_b [31:0] $end
$var integer 32 , exp_c [31:0] $end
$var integer 32 - fd [31:0] $end
$var integer 32 . line_num [31:0] $end
$var integer 32 / r [31:0] $end
$scope module uut $end
$var wire 8 0 a0 [7:0] $end
$var wire 8 1 a0_inp [7:0] $end
$var wire 8 2 a1 [7:0] $end
$var wire 8 3 a1_inp [7:0] $end
$var wire 8 4 b0 [7:0] $end
$var wire 8 5 b0_inp [7:0] $end
$var wire 8 6 b1 [7:0] $end
$var wire 8 7 b1_inp [7:0] $end
$var wire 1 ' clk $end
$var wire 8 8 rand_01 [7:0] $end
$var wire 8 9 rand_01_inp [7:0] $end
$var wire 8 : u01 [7:0] $end
$var wire 8 ; u10 [7:0] $end
$var wire 8 < z11_assgn11 [7:0] $end
$var wire 8 = z1_assgn1 [7:0] $end
$var wire 8 > z3_assgn3 [7:0] $end
$var wire 8 ? z5_assgn5 [7:0] $end
$var wire 8 @ z7_assgn7 [7:0] $end
$var wire 8 A z9_assgn9 [7:0] $end
$var wire 8 B a_neg_hpc2_w_1_order1 [7:0] $end
$var wire 8 C a_neg_hpc2_w_1_order0 [7:0] $end
$var reg 8 D a0_inp_reg [7:0] $end
$var reg 8 E a1_inp_reg [7:0] $end
$var reg 8 F a_neg_hpc2_w_1_order0_reg [7:0] $end
$var reg 8 G a_neg_hpc2_w_1_order1_reg [7:0] $end
$var reg 8 H b_share_reg_hpc2_same_shares_1_order0 [7:0] $end
$var reg 8 I b_share_reg_hpc2_same_shares_1_order1 [7:0] $end
$var reg 8 J c0 [7:0] $end
$var reg 8 K c1 [7:0] $end
$var reg 8 L rand_reg_hpc2_w_1_order0 [7:0] $end
$var reg 8 M rand_reg_hpc2_w_1_order1 [7:0] $end
$var reg 8 N temp_hpc2_v_1_order0 [7:0] $end
$var reg 8 O temp_hpc2_v_1_order1 [7:0] $end
$var reg 8 P u00 [7:0] $end
$var reg 8 Q u11 [7:0] $end
$var reg 8 R v01 [7:0] $end
$var reg 8 S v10 [7:0] $end
$var reg 8 T w01 [7:0] $end
$var reg 8 U w10 [7:0] $end
$upscope $end
$upscope $end
$enddefinitions $end
$comment Show the parameter values. $end
$dumpall
$end
#0
$dumpvars
bx U
bx T
bx S
bx R
bx Q
bx P
bx O
bx N
bx M
bx L
bx K
bx J
bx I
bx H
bx G
bx F
bx E
bx D
b0 C
b0 B
bx A
bx @
bx ?
bx >
bx =
bx <
bx ;
bx :
b0 9
b0 8
b1 7
b1 6
b1001 5
b1001 4
b10100 3
b10100 2
b1010 1
b1010 0
b1000 /
b1 .
b10000000000000000000000000000011 -
b1000 ,
b1000 +
b11110 *
b0 )
b110000100110000001011000110000100110001001011000110001000110000001011000110001000110001001011000111001001100001011011100110010001011111001100000011000100101100011000010010110001100010001011000110001100001010 (
0'
b1 &
b1001 %
b10100 $
b1010 #
bx "
bx !
$end
#5000
b0 A
b0 <
b0 @
b0 ?
b0 >
b1000 =
b1 I
b0 G
b0 M
b10100 E
b1001 O
b0 F
b0 L
b1 N
b1010 D
b1001 H
1'
#10000
0'
#15000
b0 ;
b0 :
b0 Q
b0 U
b0 S
b0 T
b0 R
b1000 P
1'
#20000
0'
#25000
b0 !
b0 K
b1000 "
b1000 J
1'
#30000
0'
#35000
1'
#40000
0'
#45000
1'
#50000
0'
#55000
b100 @
b10001 >
b10000 =
b10001 I
b100 E
b10100 O
b10001 N
b10001 D
b10100 H
1'
b101 ,
b101 +
b10101 *
b10001 7
b10001 &
b10001 6
b10100 5
b10100 %
b10100 4
b100 3
b100 $
b100 2
b10001 1
b10001 #
b10001 0
b10 .
#60000
0'
#65000
b100 ;
b10001 :
b100 S
b10001 R
b10000 P
1'
#70000
0'
#75000
b100 !
b100 K
b1 "
b1 J
1'
#80000
0'
#85000
1'
#90000
0'
#95000
1'
#100000
0'
#105000
b10000 >
b1 M
b1100 E
b10101 O
b1 L
b10000 N
b10000 D
1'
b100 ,
b11100 *
b1 9
b1 )
b1 8
b1100 3
b1100 $
b1100 2
b10000 1
b10000 #
b10000 0
b11 .
#110000
0'
#115000
b10000 :
b10000 R
1'
#120000
0'
#125000
b0 "
b0 J
1'
#130000
0'
#135000
1'
#140000
0'
#145000
1'
#150000
0'
#155000
b100 <
b1 @
b1 >
b0 =
b1100 I
b101 E
b10001 O
b1101 N
b11 D
b10000 H
1'
b11100 +
b110 *
b1100 7
b1100 &
b1100 6
b10000 5
b10000 %
b10000 4
b101 3
b101 $
b101 2
b11 1
b11 #
b11 0
b100 .
#160000
0'
#165000
b1 ;
b1 :
b100 Q
b1 S
b1 R
b0 P
1'
#170000
0'
#175000
b101 !
b101 K
b1 "
b1 J
1'
#180000
0'
#185000
1'
#190000
0'
#195000
1'
#200000
0'
#205000
b10 <
b0 @
b10 >
b10 I
b1010 E
b1 O
b11 N
b1010 D
b0 H
1'
b0 ,
b10 +
b0 *
b10 7
b10 &
b10 6
b0 5
b0 %
b0 4
b1010 3
b1010 $
b1010 2
b1010 1
b1010 #
b1010 0
b101 .
#210000
0'
#215000
b0 ;
b10 :
b10 Q
b0 S
b10 R
1'
#220000
0'
#225000
b10 !
b10 K
b10 "
b10 J
1'
#230000
0'
#235000
1'
#240000
0'
#245000
1'
#250000
0'
#255000
b101 <
b101 @
b110 >
b110 =
b1111 I
b101 E
b111 O
b1110 N
b110 D
b110 H
1'
b1 ,
b1001 +
b11 *
b1111 7
b1111 &
b1111 6
b110 5
b110 %
b110 4
b101 3
b101 $
b101 2
b110 1
b110 #
b110 0
b110 .
#260000
0'
#265000
b101 ;
b110 :
b101 Q
b101 S
b110 R
b110 P
1'
#270000
0'
#275000
b0 !
b0 K
b0 "
b0 J
1'
#280000
0'
#285000
1'
#290000
0'
#295000
1'
#300000
0'
#305000
b100 <
b0 @
b101 >
b0 =
b10100 I
b100 E
b10001 O
b10101 N
b1101 D
b10000 H
1'
b0 ,
b100 +
b1001 *
b10100 7
b10100 &
b10100 6
b10000 5
b10000 %
b10000 4
b100 3
b100 $
b100 2
b1101 1
b1101 #
b1101 0
b111 .
#310000
0'
#315000
b0 ;
b101 :
b100 Q
b0 S
b101 R
b0 P
1'
#320000
0'
#325000
b100 !
b100 K
b101 "
b101 J
1'
#330000
0'
#335000
1'
#340000
0'
#345000
1'
#350000
0'
#355000
b1000 <
b1000 @
b1000 >
b1000 =
b1000 I
b0 M
b1110 E
b1000 O
b0 L
b1000 N
b1001 D
b1000 H
1'
b0 +
b111 *
b0 9
b0 )
b0 8
b1000 7
b1000 &
b1000 6
b1000 5
b1000 %
b1000 4
b1110 3
b1110 $
b1110 2
b1001 1
b1001 #
b1001 0
b1000 .
#360000
0'
#365000
b1000 ;
b1000 :
b1000 Q
b1000 S
b1000 R
b1000 P
1'
#370000
0'
#375000
b0 !
b0 K
b0 "
b0 J
1'
#380000
0'
#385000
1'
#390000
0'
#395000
1'
#400000
0'
#405000
b11 <
b11 @
b10 >
b10 =
b11 I
b1 M
b11 E
b11 O
b1 L
b10 N
b110 D
b10 H
1'
b1 ,
b1 +
b101 *
b1 9
b1 )
b1 8
b11 7
b11 &
b11 6
b10 5
b10 %
b10 4
b11 3
b11 $
b11 2
b110 1
b110 #
b110 0
b1001 .
#410000
0'
#415000
b11 ;
b10 :
b11 Q
b11 S
b10 R
b10 P
1'
#420000
0'
#425000
1'
#430000
0'
#435000
1'
#440000
0'
#445000
1'
#450000
0'
#455000
b100 <
b10 @
b0 >
b1 =
b100 I
b0 M
b110 E
b0 L
b100 N
b1001 D
b11 H
1'
b111 ,
b111 +
b1111 *
b0 9
b0 )
b0 8
b100 7
b100 &
b100 6
b11 5
b11 %
b11 4
b110 3
b110 $
b110 2
b1001 1
b1001 #
b1001 0
b1010 .
#460000
0'
#465000
b10 ;
b0 :
b100 Q
b10 S
b0 R
b1 P
1'
#470000
0'
#475000
b110 !
b110 K
b1 "
b1 J
1'
#480000
0'
#485000
1'
#490000
0'
#495000
1'
#500000
0'
#505000
b1000 <
b100 @
b1000 >
b101 =
b1011 I
b1 M
b1100 E
b100 O
b1 L
b1010 N
b1101 D
b101 H
1'
b0 ,
b1110 +
b1 *
b1 9
b1 )
b1 8
b1011 7
b1011 &
b1011 6
b101 5
b101 %
b101 4
b1100 3
b1100 $
b1100 2
b1101 1
b1101 #
b1101 0
b1011 .
#510000
0'
#515000
b100 ;
b1000 :
b1000 Q
b100 S
b1000 R
b101 P
1'
#520000
0'
#525000
b1100 !
b1100 K
b1101 "
b1101 J
1'
#530000
0'
#535000
1'
#540000
0'
#545000
1'
#550000
0'
#555000
b0 <
b10001 @
b1 >
b10000 =
b0 I
b10001 E
b10101 O
b1 N
b10001 D
b10100 H
1'
b10100 +
b0 *
b0 7
b0 &
b0 6
b10100 5
b10100 %
b10100 4
b10001 3
b10001 $
b10001 2
b10001 1
b10001 #
b10001 0
b1100 .
#560000
0'
#565000
b10001 ;
b1 :
b0 Q
b10001 S
b1 R
b10000 P
1'
#570000
0'
#575000
b10001 !
b10001 K
b10001 "
b10001 J
1'
#580000
0'
#585000
1'
#590000
0'
#595000
1'
#600000
0'
#605000
b1001 <
b1100 @
b0 >
b0 =
b1011 I
b1101 E
b1100 O
b1010 N
b10000 D
b1101 H
1'
b100 ,
b110 +
b11101 *
b1011 7
b1011 &
b1011 6
b1101 5
b1101 %
b1101 4
b1101 3
b1101 $
b1101 2
b10000 1
b10000 #
b10000 0
b1101 .
#610000
0'
#615000
b1100 ;
b0 :
b1001 Q
b1100 S
b0 R
b0 P
1'
#620000
0'
#625000
b101 !
b101 K
b0 "
b0 J
1'
#630000
0'
#635000
1'
#640000
0'
#645000
1'
#650000
0'
#655000
b0 <
b100 @
b1 I
b0 M
b10100 E
b100 O
b0 L
b1 N
b100 H
1'
b101 +
b100 *
b0 9
b0 )
b0 8
b1 7
b1 &
b1 6
b100 5
b100 %
b100 4
b10100 3
b10100 $
b10100 2
b1110 .
#660000
0'
#665000
b100 ;
b0 Q
b100 S
1'
#670000
0'
#675000
b100 !
b100 K
1'
#680000
0'
#685000
1'
#690000
0'
#695000
1'
#700000
0'
#705000
b110 <
b0 @
b1110 >
b1001 =
b1111 I
b1 M
b110 E
b1000 O
b1 L
b1110 N
b1111 D
b1001 H
1'
b0 ,
b110 +
b1001 *
b1 9
b1 )
b1 8
b1111 7
b1111 &
b1111 6
b1001 5
b1001 %
b1001 4
b110 3
b110 $
b110 2
b1111 1
b1111 #
b1111 0
b1111 .
#710000
0'
#715000
b0 ;
b1110 :
b110 Q
b0 S
b1110 R
b1001 P
1'
#720000
0'
#725000
b110 !
b110 K
b111 "
b111 J
1'
#730000
0'
#735000
1'
#740000
0'
#745000
1'
#750000
0'
#755000
b1 <
b10 @
b1 >
b100 =
b1001 I
b0 M
b11 E
b1110 O
b0 L
b1001 N
b101 D
b1110 H
1'
b110 ,
b111 +
b110 *
b0 9
b0 )
b0 8
b1001 7
b1001 &
b1001 6
b1110 5
b1110 %
b1110 4
b11 3
b11 $
b11 2
b101 1
b101 #
b101 0
b10000 .
#760000
0'
#765000
b10 ;
b1 :
b1 Q
b10 S
b1 R
b100 P
1'
#770000
0'
#775000
b11 !
b11 K
b101 "
b101 J
1'
#780000
0'
#785000
1'
#790000
0'
#795000
1'
#800000
0'
#805000
b100 <
b10000 @
b1001 >
b0 =
b1101 I
b10100 E
b10010 O
b1101 N
b1001 D
b10010 H
1'
b11101 ,
b11111 +
b11101 *
b1101 7
b1101 &
b1101 6
b10010 5
b10010 %
b10010 4
b10100 3
b10100 $
b10100 2
b1001 1
b1001 #
b1001 0
b10001 .
#810000
0'
#815000
b10000 ;
b1001 :
b100 Q
b10000 S
b1001 R
b0 P
1'
#820000
0'
#825000
b10100 !
b10100 K
b1001 "
b1001 J
1'
#830000
0'
#835000
1'
#840000
0'
#845000
1'
#850000
0'
#855000
b10 <
b101 @
b1000 >
b100 =
b1010 I
b1 M
b111 E
b101 O
b1 L
b1011 N
b1100 D
b100 H
1'
b1010 ,
b1110 +
b1011 *
b1 9
b1 )
b1 8
b1010 7
b1010 &
b1010 6
b100 5
b100 %
b100 4
b111 3
b111 $
b111 2
b1100 1
b1100 #
b1100 0
b10010 .
#860000
0'
#865000
b101 ;
b1000 :
b10 Q
b101 S
b1000 R
b100 P
1'
#870000
0'
#875000
b111 !
b111 K
b1100 "
b1100 J
1'
#880000
0'
#885000
1'
#890000
0'
#895000
1'
#900000
0'
#905000
b101 <
b1 @
b100 >
b0 =
b101 I
b101 E
b10011 O
b100 N
b1101 D
b10010 H
1'
b0 ,
b10111 +
b1000 *
b101 7
b101 &
b101 6
b10010 5
b10010 %
b10010 4
b101 3
b101 $
b101 2
b1101 1
b1101 #
b1101 0
b10011 .
#910000
0'
#915000
b1 ;
b100 :
b101 Q
b1 S
b100 R
b0 P
1'
#920000
0'
#925000
b100 !
b100 K
b100 "
b100 J
1'
#930000
0'
#935000
1'
#940000
0'
#945000
1'
#950000
0'
#955000
b11 <
b11 @
b1000 >
b1000 =
b1011 I
b10011 E
b1111 O
b1010 N
b1000 D
b1110 H
1'
b1 ,
b101 +
b11011 *
b1011 7
b1011 &
b1011 6
b1110 5
b1110 %
b1110 4
b10011 3
b10011 $
b10011 2
b1000 1
b1000 #
b1000 0
b10100 .
#960000
0'
#965000
b11 ;
b1000 :
b11 Q
b11 S
b1000 R
b1000 P
1'
#970000
0'
#975000
b0 !
b0 K
b0 "
b0 J
1'
#980000
0'
#985000
1'
#990000
0'
#995000
1'
#1000000
0'
#1005000
b101 <
b100 @
b100 >
b100 =
b111 I
b0 M
b101 E
b100 O
b0 L
b111 N
b10100 D
b100 H
1'
b11 +
b10001 *
b0 9
b0 )
b0 8
b111 7
b111 &
b111 6
b100 5
b100 %
b100 4
b101 3
b101 $
b101 2
b10100 1
b10100 #
b10100 0
b10101 .
#1010000
0'
#1015000
b100 ;
b100 :
b101 Q
b100 S
b100 R
b100 P
1'
#1020000
0'
#1025000
b1 !
b1 K
1'
#1030000
0'
#1035000
1'
#1040000
0'
#1045000
1'
#1050000
0'
#1055000
b100 <
b0 @
b1 >
b0 =
b100 I
b1 M
b1100 E
b1 O
b1 L
b101 N
b1011 D
b0 H
1'
b100 ,
b100 +
b111 *
b1 9
b1 )
b1 8
b100 7
b100 &
b100 6
b0 5
b0 %
b0 4
b1100 3
b1100 $
b1100 2
b1011 1
b1011 #
b1011 0
b10110 .
#1060000
0'
#1065000
b0 ;
b1 :
b100 Q
b0 S
b1 R
b0 P
1'
#1070000
0'
#1075000
b100 !
b100 K
b1 "
b1 J
1'
#1080000
0'
#1085000
1'
#1090000
0'
#1095000
1'
#1100000
0'
#1105000
b0 <
b10 >
b10 =
b10 I
b0 M
b10010 O
b0 L
b10 N
b110 D
b10010 H
1'
b0 ,
b10000 +
b1010 *
b0 9
b0 )
b0 8
b10 7
b10 &
b10 6
b10010 5
b10010 %
b10010 4
b110 1
b110 #
b110 0
b10111 .
#1110000
0'
#1115000
b10 :
b0 Q
b10 R
b10 P
1'
#1120000
0'
#1125000
b0 !
b0 K
b0 "
b0 J
1'
#1130000
0'
#1135000
1'
#1140000
0'
#1145000
1'
#1150000
0'
#1155000
b1000 <
b100 @
b111 =
b1011 I
b1 M
b110 O
b1 L
b1010 N
b111 D
b111 H
1'
b1000 ,
b1100 +
b1011 *
b1 9
b1 )
b1 8
b1011 7
b1011 &
b1011 6
b111 5
b111 %
b111 4
b111 1
b111 #
b111 0
b11000 .
#1160000
0'
#1165000
b100 ;
b1000 Q
b100 S
b111 P
1'
#1170000
0'
#1175000
b1100 !
b1100 K
b101 "
b101 J
1'
#1180000
0'
#1185000
1'
#1190000
0'
#1195000
1'
#1200000
0'
#1205000
b1 <
b1 @
b1000 >
b100 =
b1001 I
b0 M
b1 E
b101 O
b0 L
b1001 N
b1100 D
b101 H
1'
b1100 ,
b1101 *
b0 9
b0 )
b0 8
b1001 7
b1001 &
b1001 6
b101 5
b101 %
b101 4
b1 3
b1 $
b1 2
b1100 1
b1100 #
b1100 0
b11001 .
#1210000
0'
#1215000
b1 ;
b1000 :
b1 Q
b1 S
b1000 R
b100 P
1'
#1220000
0'
#1225000
b0 !
b0 K
b1100 "
b1100 J
1'
#1230000
0'
#1235000
1'
#1240000
0'
#1245000
1'
#1250000
0'
#1255000
b0 <
b0 @
b100 >
b0 =
b1101 I
b10000 E
b11 O
b1101 N
b10100 D
b11 H
1'
b100 ,
b1110 +
b100 *
b1101 7
b1101 &
b1101 6
b11 5
b11 %
b11 4
b10000 3
b10000 $
b10000 2
b10100 1
b10100 #
b10100 0
b11010 .
#1260000
0'
#1265000
b0 ;
b100 :
b0 Q
b0 S
b100 R
b0 P
1'
#1270000
0'
#1275000
b100 "
b100 J
1'
#1280000
0'
#1285000
1'
#1290000
0'
#1295000
1'
#1300000
0'
#1305000
b1 <
b1001 @
b1 >
b1 =
b101 I
b1011 E
b1001 O
b101 N
b1 D
b1001 H
1'
b1000 ,
b1100 +
b1010 *
b101 7
b101 &
b101 6
b1001 5
b1001 %
b1001 4
b1011 3
b1011 $
b1011 2
b1 1
b1 #
b1 0
b11011 .
#1310000
0'
#1315000
b1001 ;
b1 :
b1 Q
b1001 S
b1 R
b1 P
1'
#1320000
0'
#1325000
b1000 !
b1000 K
b0 "
b0 J
1'
#1330000
0'
#1335000
1'
#1340000
0'
#1345000
1'
#1350000
0'
#1355000
b100 <
b110 @
b100 >
b110 =
b100 I
b1 M
b1110 E
b110 O
b1 L
b110 D
b111 H
1'
b0 ,
b11 +
b1000 *
b1 9
b1 )
b1 8
b100 7
b100 &
b100 6
b111 5
b111 %
b111 4
b1110 3
b1110 $
b1110 2
b110 1
b110 #
b110 0
b11100 .
#1360000
0'
#1365000
b110 ;
b100 :
b100 Q
b110 S
b100 R
b110 P
1'
#1370000
0'
#1375000
b10 !
b10 K
b10 "
b10 J
1'
#1380000
0'
#1385000
1'
#1390000
0'
#1395000
1'
#1400000
0'
#1405000
b1 <
b1001 @
b0 >
b0 =
b1 I
b1001 E
b1001 O
b0 N
b1000 H
1'
b1001 ,
b1001 +
b1111 *
b1 7
b1 &
b1 6
b1000 5
b1000 %
b1000 4
b1001 3
b1001 $
b1001 2
b11101 .
#1410000
0'
#1415000
b1001 ;
b0 :
b1 Q
b1001 S
b0 R
b0 P
1'
#1420000
0'
#1425000
b1000 !
b1000 K
b0 "
b0 J
1'
#1430000
0'
#1435000
1'
#1440000
0'
#1445000
1'
#1450000
0'
#1455000
b111 <
b10 @
b1000 >
b1111 I
b0 M
b111 E
b10 O
b0 L
b1111 N
b1000 D
b10 H
1'
b1101 ,
b1101 +
b0 9
b0 )
b0 8
b1111 7
b1111 &
b1111 6
b10 5
b10 %
b10 4
b111 3
b111 $
b111 2
b1000 1
b1000 #
b1000 0
b11110 .
#1460000
0'
#1465000
b10 ;
b1000 :
b111 Q
b10 S
b1000 R
1'
#1470000
0'
#1475000
b101 !
b101 K
b1000 "
b1000 J
1'
#1480000
0'
#1485000
1'
#1490000
0'
#1495000
1'
#1500000
0'
#1505000
b110 <
b10 >
b10 =
b111 I
b1 M
b110 E
b10011 O
b1 L
b110 N
b10 D
b10010 H
1'
b100 ,
b10101 +
b100 *
b1 9
b1 )
b1 8
b111 7
b111 &
b111 6
b10010 5
b10010 %
b10010 4
b110 3
b110 $
b110 2
b10 1
b10 #
b10 0
b11111 .
#1510000
0'
#1515000
b10 :
b110 Q
b10 R
b10 P
1'
#1520000
0'
#1525000
b100 !
b100 K
b0 "
b0 J
1'
#1530000
0'
#1535000
1'
#1540000
0'
#1545000
1'
#1550000
0'
#1555000
b100 <
b110 @
b1 >
b0 =
b100 I
b111 O
b101 N
b1 D
b110 H
1'
b10 ,
b10 +
b111 *
b100 7
b100 &
b100 6
b110 5
b110 %
b110 4
b1 1
b1 #
b1 0
b100000 .
#1560000
0'
#1565000
b110 ;
b1 :
b100 Q
b110 S
b1 R
b0 P
1'
#1570000
0'
#1575000
b10 !
b10 K
b1 "
b1 J
1'
#1580000
0'
#1585000
1'
#1590000
0'
#1595000
1'
#1600000
0'
#1605000
b1 <
b1 @
b0 >
b10001 I
b0 M
b11 E
b101 O
b0 L
b10001 N
b1010 D
b101 H
1'
b0 ,
b10100 +
b1001 *
b0 9
b0 )
b0 8
b10001 7
b10001 &
b10001 6
b101 5
b101 %
b101 4
b11 3
b11 $
b11 2
b1010 1
b1010 #
b1010 0
b100001 .
#1610000
0'
#1615000
b1 ;
b0 :
b1 Q
b1 S
b0 R
1'
#1620000
0'
#1625000
b0 !
b0 K
b0 "
b0 J
1'
#1630000
0'
#1635000
1'
#1640000
0'
#1645000
1'
#1650000
0'
#1655000
b1 A
b0 <
b0 @
b1000 I
b1 G
b1 M
b0 E
b1 O
b1 L
b1001 N
b10 D
b0 H
1'
b1000 +
b10 *
b1 9
b1 )
b1 8
b1000 7
b1000 &
b1000 6
b0 5
b0 %
b0 4
b1 B
b0 3
b0 $
b0 2
b10 1
b10 #
b10 0
b100010 .
#1660000
0'
#1665000
b0 Q
b1 U
b0 S
1'
#1670000
0'
#1675000
b1 !
b1 K
1'
#1680000
0'
#1685000
1'
#1690000
0'
#1695000
1'
#1700000
0'
#1705000
b0 A
b10 <
b1100 @
b1 >
b10 I
b0 G
b1110 E
b1101 O
b11 N
b10001 D
b1100 H
1'
b1110 ,
b1110 +
b11111 *
b10 7
b10 &
b10 6
b1100 5
b1100 %
b1100 4
b0 B
b1110 3
b1110 $
b1110 2
b10001 1
b10001 #
b10001 0
b100011 .
#1710000
0'
#1715000
b1100 ;
b1 :
b10 Q
b0 U
b1100 S
b1 R
1'
#1720000
0'
#1725000
b1110 !
b1110 K
b1 "
b1 J
1'
#1730000
0'
#1735000
1'
#1740000
0'
#1745000
1'
#1750000
0'
#1755000
b0 @
b0 >
b0 M
b1010 E
b10100 O
b1 F
b0 L
b10 N
b0 D
b10100 H
1'
b10 ,
b10110 +
b1010 *
b0 9
b0 )
b0 8
b10100 5
b10100 %
b10100 4
b1010 3
b1010 $
b1010 2
b1 C
b0 1
b0 #
b0 0
b100100 .
#1760000
0'
#1765000
b0 ;
b0 :
b0 S
b0 R
1'
#1770000
0'
#1775000
b10 !
b10 K
b0 "
b0 J
1'
#1780000
0'
#1785000
1'
#1790000
0'
#1795000
1'
#1800000
0'
#1805000
b0 <
b10 @
b1101 I
b1 M
b10 E
b111 O
b0 F
b1 L
b1100 N
b10000 D
b110 H
1'
b1011 +
b10010 *
b1 9
b1 )
b1 8
b1101 7
b1101 &
b1101 6
b110 5
b110 %
b110 4
b10 3
b10 $
b10 2
b0 C
b10000 1
b10000 #
b10000 0
b100101 .
#1810000
0'
#1815000
b10 ;
b0 Q
b10 S
1'
#1820000
0'
#1825000
1'
#1830000
0'
#1835000
1'
#1840000
0'
#1845000
1'
#1850000
0'
#1855000
b10 <
b1100 @
b10 >
b1 =
b11 I
b1110 E
b1100 O
b10 N
b10011 D
b1101 H
1'
b1100 ,
b1110 +
b11101 *
b11 7
b11 &
b11 6
b1101 5
b1101 %
b1101 4
b1110 3
b1110 $
b1110 2
b10011 1
b10011 #
b10011 0
b100110 .
#1860000
0'
#1865000
b1100 ;
b10 :
b10 Q
b1100 S
b10 R
b1 P
1'
#1870000
0'
#1875000
b1110 !
b1110 K
b11 "
b11 J
1'
#1880000
0'
#1885000
1'
#1890000
0'
#1895000
1'
#1900000
0'
#1905000
b1011 <
b0 @
b1010 >
b0 =
b1111 I
b0 M
b1011 E
b10100 O
b0 L
b1111 N
b1010 D
b10100 H
1'
b1 ,
b11011 +
b1 *
b0 9
b0 )
b0 8
b1111 7
b1111 &
b1111 6
b10100 5
b10100 %
b10100 4
b1011 3
b1011 $
b1011 2
b1010 1
b1010 #
b1010 0
b100111 .
#1910000
0'
#1915000
b0 ;
b1010 :
b1011 Q
b0 S
b1010 R
b0 P
1'
#1920000
0'
#1925000
b1011 !
b1011 K
b1010 "
b1010 J
1'
#1930000
0'
#1935000
1'
#1940000
0'
#1945000
1'
#1950000
0'
