src/Testing/Tester/test.v
module test(
    clk,
    a_0,
    a_1,
    b_0,
    b_1,
    c_0,
    c_1,
    d_0,
    d_1,
    rand_2,
    rand_1,
    w_0,
    w_1
);
//INPUTS
    input clk;
    input  [7:0] a_0;
    input  [7:0] a_1;
    input  [7:0] b_0;
    input  [7:0] b_1;
    input  [7:0] c_0;
    input  [7:0] c_1;
    input  [7:0] d_0;
    input  [7:0] d_1;
    input  [7:0] rand_2;
    input  [7:0] rand_1;
//OUTPUTS
    output reg  [7:0] w_0;
    output reg  [7:0] w_1;
//Intermediate values
    wire [7:0] a_0_inp;
    wire [7:0] a_1_inp;
    wire [7:0] b_0_inp;
    wire [7:0] b_1_inp;
    wire [7:0] c_0_inp;
    wire [7:0] c_1_inp;
    wire [7:0] d_0_inp;
    wire [7:0] d_1_inp;
    wire [7:0] rand_2_inp;
    wire [7:0] rand_1_inp;
    wire [7:0] a_inp_0;
    wire [7:0] a_inp_1;
    wire [7:0] b_inp_0;
    wire [7:0] b_inp_1;
    wire [7:0] c_inp_0;
    wire [7:0] c_inp_1;
    wire [7:0] d_inp_0;
    wire [7:0] d_inp_1;
    reg [7:0] b_share_reg_hpc2_same_shares_1_order0_HPC20;
    reg [7:0] a_inp_0_reg;
    wire [7:0] z1_assgn1;
    reg [7:0] u00_HPC20;
    reg [7:0] temp_hpc2_v_1_order0_HPC20;
    wire [7:0] z3_assgn3;
    reg [7:0] v01_HPC20;
    reg [7:0] rand_reg_hpc2_w_1_order0_HPC20;
    wire [7:0] a_neg_hpc2_w_1_order0_HPC20;
    reg [7:0] a_neg_hpc2_w_1_order0_HPC20_reg;
    wire [7:0] z5_assgn5;
    reg [7:0] w01_HPC20;
    wire [7:0] u01_HPC20;
    reg [7:0] temp_hpc2_v_1_order1_HPC20;
    reg [7:0] a_inp_1_reg;
    wire [7:0] z7_assgn7;
    reg [7:0] v10_HPC20;
    reg [7:0] rand_reg_hpc2_w_1_order1_HPC20;
    wire [7:0] a_neg_hpc2_w_1_order1_HPC20;
    reg [7:0] a_neg_hpc2_w_1_order1_HPC20_reg;
    wire [7:0] z9_assgn9;
    reg [7:0] w10_HPC20;
    wire [7:0] u10_HPC20;
    reg [7:0] b_share_reg_hpc2_same_shares_1_order1_HPC20;
    wire [7:0] z11_assgn11;
    reg [7:0] u11_HPC20;
    wire [7:0] x_0;
    wire [7:0] x_1;
    reg [7:0] b_share_reg_hpc2_same_shares_1_order0_HPC21;
    reg [7:0] c_inp_0_reg;
    wire [7:0] z13_assgn13;
    reg [7:0] u00_HPC21;
    reg [7:0] temp_hpc2_v_1_order0_HPC21;
    wire [7:0] z15_assgn15;
    reg [7:0] v01_HPC21;
    reg [7:0] rand_reg_hpc2_w_1_order0_HPC21;
    wire [7:0] a_neg_hpc2_w_1_order0_HPC21;
    reg [7:0] a_neg_hpc2_w_1_order0_HPC21_reg;
    wire [7:0] z17_assgn17;
    reg [7:0] w01_HPC21;
    wire [7:0] u01_HPC21;
    reg [7:0] temp_hpc2_v_1_order1_HPC21;
    reg [7:0] c_inp_1_reg;
    wire [7:0] z19_assgn19;
    reg [7:0] v10_HPC21;
    reg [7:0] rand_reg_hpc2_w_1_order1_HPC21;
    wire [7:0] a_neg_hpc2_w_1_order1_HPC21;
    reg [7:0] a_neg_hpc2_w_1_order1_HPC21_reg;
    wire [7:0] z21_assgn21;
    reg [7:0] w10_HPC21;
    wire [7:0] u10_HPC21;
    reg [7:0] b_share_reg_hpc2_same_shares_1_order1_HPC21;
    wire [7:0] z23_assgn23;
    reg [7:0] u11_HPC21;
    wire [7:0] y_0;
    wire [7:0] y_1;

    assign a_0_inp = a_0;
    assign a_1_inp = a_1;
    assign b_0_inp = b_0;
    assign b_1_inp = b_1;
    assign c_0_inp = c_0;
    assign c_1_inp = c_1;
    assign d_0_inp = d_0;
    assign d_1_inp = d_1;
    assign rand_2_inp = rand_2;
    assign rand_1_inp = rand_1;
    assign a_inp_0 = a_0_inp;
    assign a_inp_1 = a_1_inp;
    assign b_inp_0 = b_0_inp;
    assign b_inp_1 = b_1_inp;
    assign c_inp_0 = c_0_inp;
    assign c_inp_1 = c_1_inp;
    assign d_inp_0 = d_0_inp;
    assign d_inp_1 = d_1_inp;
    assign z1_assgn1 = (a_inp_0_reg & b_share_reg_hpc2_same_shares_1_order0_HPC20);
    assign z3_assgn3 = (temp_hpc2_v_1_order0_HPC20 & a_inp_0_reg);
    assign a_neg_hpc2_w_1_order0_HPC20 = ~a_inp_0;
    assign z5_assgn5 = (a_neg_hpc2_w_1_order0_HPC20_reg & rand_reg_hpc2_w_1_order0_HPC20);
    assign u01_HPC20 = (v01_HPC20 ^ w01_HPC20);
    assign z7_assgn7 = (temp_hpc2_v_1_order1_HPC20 & a_inp_1_reg);
    assign a_neg_hpc2_w_1_order1_HPC20 = ~a_inp_1;
    assign z9_assgn9 = (a_neg_hpc2_w_1_order1_HPC20_reg & rand_reg_hpc2_w_1_order1_HPC20);
    assign u10_HPC20 = (v10_HPC20 ^ w10_HPC20);
    assign z11_assgn11 = (a_inp_1_reg & b_share_reg_hpc2_same_shares_1_order1_HPC20);
    assign x_0 = (u00_HPC20 ^ u01_HPC20);
    assign x_1 = (u10_HPC20 ^ u11_HPC20);
    assign z13_assgn13 = (c_inp_0_reg & b_share_reg_hpc2_same_shares_1_order0_HPC21);
    assign z15_assgn15 = (temp_hpc2_v_1_order0_HPC21 & c_inp_0_reg);
    assign a_neg_hpc2_w_1_order0_HPC21 = ~c_inp_0;
    assign z17_assgn17 = (a_neg_hpc2_w_1_order0_HPC21_reg & rand_reg_hpc2_w_1_order0_HPC21);
    assign u01_HPC21 = (v01_HPC21 ^ w01_HPC21);
    assign z19_assgn19 = (temp_hpc2_v_1_order1_HPC21 & c_inp_1_reg);
    assign a_neg_hpc2_w_1_order1_HPC21 = ~c_inp_1;
    assign z21_assgn21 = (a_neg_hpc2_w_1_order1_HPC21_reg & rand_reg_hpc2_w_1_order1_HPC21);
    assign u10_HPC21 = (v10_HPC21 ^ w10_HPC21);
    assign z23_assgn23 = (c_inp_1_reg & b_share_reg_hpc2_same_shares_1_order1_HPC21);
    assign y_0 = (u00_HPC21 ^ u01_HPC21);
    assign y_1 = (u10_HPC21 ^ u11_HPC21);

    always @(posedge clk) begin
        b_share_reg_hpc2_same_shares_1_order0_HPC20 <= b_inp_0;
        a_inp_0_reg <= a_inp_0;
        u00_HPC20 <= z1_assgn1;
        temp_hpc2_v_1_order0_HPC20 <= (b_inp_1 ^ rand_1_inp);
        v01_HPC20 <= z3_assgn3;
        rand_reg_hpc2_w_1_order0_HPC20 <= rand_1_inp;
        a_neg_hpc2_w_1_order0_HPC20_reg <= a_neg_hpc2_w_1_order0_HPC20;
        w01_HPC20 <= z5_assgn5;
        temp_hpc2_v_1_order1_HPC20 <= (b_inp_0 ^ rand_1_inp);
        a_inp_1_reg <= a_inp_1;
        v10_HPC20 <= z7_assgn7;
        rand_reg_hpc2_w_1_order1_HPC20 <= rand_1_inp;
        a_neg_hpc2_w_1_order1_HPC20_reg <= a_neg_hpc2_w_1_order1_HPC20;
        w10_HPC20 <= z9_assgn9;
        b_share_reg_hpc2_same_shares_1_order1_HPC20 <= b_inp_1;
        u11_HPC20 <= z11_assgn11;
        b_share_reg_hpc2_same_shares_1_order0_HPC21 <= d_inp_0;
        c_inp_0_reg <= c_inp_0;
        u00_HPC21 <= z13_assgn13;
        temp_hpc2_v_1_order0_HPC21 <= (d_inp_1 ^ rand_2_inp);
        v01_HPC21 <= z15_assgn15;
        rand_reg_hpc2_w_1_order0_HPC21 <= rand_2_inp;
        a_neg_hpc2_w_1_order0_HPC21_reg <= a_neg_hpc2_w_1_order0_HPC21;
        w01_HPC21 <= z17_assgn17;
        temp_hpc2_v_1_order1_HPC21 <= (d_inp_0 ^ rand_2_inp);
        c_inp_1_reg <= c_inp_1;
        v10_HPC21 <= z19_assgn19;
        rand_reg_hpc2_w_1_order1_HPC21 <= rand_2_inp;
        a_neg_hpc2_w_1_order1_HPC21_reg <= a_neg_hpc2_w_1_order1_HPC21;
        w10_HPC21 <= z21_assgn21;
        b_share_reg_hpc2_same_shares_1_order1_HPC21 <= d_inp_1;
        u11_HPC21 <= z23_assgn23;
        w_0 <= (x_0 ^ y_0);
        w_1 <= (x_1 ^ y_1);
    end

endmodule

src/Testing/Tester/test_tb.v
`timescale 1ns/1ps

module test_tb;

    // DUT Inputs
    reg clk;
    reg [7:0] a_0;
    reg [7:0] a_1;
    reg [7:0] d_0;
    reg [7:0] d_1;
    reg [7:0] b_0;
    reg [7:0] b_1;
    reg [7:0] c_0;
    reg [7:0] c_1;
    reg [7:0] rand_1;
    reg [7:0] rand_2;
    // reg [7:0] rand_3;
    // reg [7:0] rand_4;
    // reg [7:0] rand_5;
    // reg [7:0] rand_6;
    // reg [7:0] rand_7;
    // reg [7:0] rand_8;

 
    // DUT Outputs
    wire [7:0] w_0;
    wire [7:0] w_1;

    // Testbench Variables
    integer fd, r;
    integer line_num;
    integer a, b, c, d, out, out2, x, timeout_counter;
    reg [8*256:0] header;

    // Instantiate the design under test (DUT)
    test uut (
        .clk(clk),
        .a_0(a_0), .a_1(a_1),
        .d_0(d_0), .d_1(d_1),
        .b_0(b_0), .b_1(b_1),
        .c_0(c_0), .c_1(c_1),
        .rand_1(rand_1), .rand_2(rand_2), //.rand_3(rand_3),
        // .rand_4(rand_4), .rand_5(rand_5), .rand_6(rand_6),.rand_7(rand_7),.rand_8(rand_8),
        .w_0(w_0), .w_1(w_1)
    );

    // Clock Generation (100 MHz)
    initial begin
        clk = 0;
        forever #5 clk = ~clk; // 10ns period
    end

    // Stimulus and Checking Process
    initial begin
        $dumpfile("test_tb.vcd");
        $dumpvars(0, test_tb);

        // --- PHASE 1: RESET THE DUT ---
        $display("Starting simulation with reset phase...");
        a_0 = 8'd0; a_1 = 8'd0; d_0 = 8'd0; d_1 = 8'd0;
        b_0 = 8'd0; b_1 = 8'd0; c_0 = 8'd0; c_1 = 8'd0;
        rand_1 = 8'd0; rand_2 = 8'd0; //rand_3 = 8'd0;
        // rand_4 = 8'd0; rand_5 = 8'd0; rand_6 = 8'd0;
        // rand_7 = 8'd0; rand_8 = 8'd0;
        
        // Hold inputs at 0 for 30 cycles to flush the pipeline
        repeat (30) @(posedge clk);
        $display("Reset phase complete. Starting test vectors...");
        // -----------------------------

        fd = $fopen("test_vectors.csv", "r");
        if (fd == 0) begin
            $display("ERROR: Could not open test_vectors.csv");
            $finish;
        end

        r = $fgets(header, fd);
        line_num = 0;

        // --- PHASE 2: PROCESS TEST VECTORS ---
        while (!$feof(fd)) begin
            line_num = line_num + 1;
            
            r = $fscanf(fd, "%d,%d,%d,%d,%d,%d,%d,%d,%d,%d,%d,%d,%d,%d,%d,%d\n",
                        a_0, a_1, b_0, b_1, c_0, c_1, d_0, d_1,
                        rand_2, rand_1,
                        a, b, c, d, out,out2);

            // Latch the new inputs on the next clock edge
            @(posedge clk);

            // --- Wait-for-Result Loop with a 200-cycle Timeout ---
            // integer timeout_counter;
            timeout_counter = 0;
            
            while ((w_0 ^ w_1) != out && timeout_counter < 200) begin
                @(posedge clk);
                timeout_counter = timeout_counter + 1;
            end
            // ----------------------------------------------------

            // Capture the final result
            x = (w_0 ^ w_1);

            // Check and display the result
            if (timeout_counter >= 200) begin
                $display("Line %0d: FAIL (Timeout!) expected=%0d  return=%0d", line_num, out, x);
            end else if (x == out) begin // Use === for safe X/Z checking
                $display("Line %0d: PASS (found in %0d cycles) expected=%0d  return=%0d",
                         line_num, timeout_counter + 1, out, x);
            end else begin
                // This case should not be reached due to the while loop condition
                 $display("Line %0d: FAIL (Logic Error!) expected=%0d  return=%0d", line_num, out, x);
            end
        end

        $fclose(fd);
        $display("All test vectors processed.");
        #20 $finish;
    end

endmodule

src/Testing/Tester/test_tb.vcd
$date
	Sat Aug 30 11:58:54 2025
$end
$version
	Icarus Verilog
$end
$timescale
	1ps
$end
$scope module test_tb $end
$var wire 8 ! w_1 [7:0] $end
$var wire 8 " w_0 [7:0] $end
$var reg 8 # a_0 [7:0] $end
$var reg 8 $ a_1 [7:0] $end
$var reg 8 % b_0 [7:0] $end
$var reg 8 & b_1 [7:0] $end
$var reg 8 ' c_0 [7:0] $end
$var reg 8 ( c_1 [7:0] $end
$var reg 1 ) clk $end
$var reg 8 * d_0 [7:0] $end
$var reg 8 + d_1 [7:0] $end
$var reg 2049 , header [2048:0] $end
$var reg 8 - rand_1 [7:0] $end
$var reg 8 . rand_2 [7:0] $end
$var integer 32 / a [31:0] $end
$var integer 32 0 b [31:0] $end
$var integer 32 1 c [31:0] $end
$var integer 32 2 d [31:0] $end
$var integer 32 3 fd [31:0] $end
$var integer 32 4 line_num [31:0] $end
$var integer 32 5 out [31:0] $end
$var integer 32 6 out2 [31:0] $end
$var integer 32 7 r [31:0] $end
$var integer 32 8 timeout_counter [31:0] $end
$var integer 32 9 x [31:0] $end
$scope module uut $end
$var wire 8 : a_0 [7:0] $end
$var wire 8 ; a_0_inp [7:0] $end
$var wire 8 < a_1 [7:0] $end
$var wire 8 = a_1_inp [7:0] $end
$var wire 8 > a_inp_0 [7:0] $end
$var wire 8 ? a_inp_1 [7:0] $end
$var wire 8 @ a_neg_hpc2_w_1_order0_HPC20 [7:0] $end
$var wire 8 A a_neg_hpc2_w_1_order0_HPC21 [7:0] $end
$var wire 8 B a_neg_hpc2_w_1_order1_HPC20 [7:0] $end
$var wire 8 C a_neg_hpc2_w_1_order1_HPC21 [7:0] $end
$var wire 8 D b_0 [7:0] $end
$var wire 8 E b_0_inp [7:0] $end
$var wire 8 F b_1 [7:0] $end
$var wire 8 G b_1_inp [7:0] $end
$var wire 8 H b_inp_0 [7:0] $end
$var wire 8 I b_inp_1 [7:0] $end
$var wire 8 J c_0 [7:0] $end
$var wire 8 K c_0_inp [7:0] $end
$var wire 8 L c_1 [7:0] $end
$var wire 8 M c_1_inp [7:0] $end
$var wire 8 N c_inp_0 [7:0] $end
$var wire 8 O c_inp_1 [7:0] $end
$var wire 1 ) clk $end
$var wire 8 P d_0 [7:0] $end
$var wire 8 Q d_0_inp [7:0] $end
$var wire 8 R d_1 [7:0] $end
$var wire 8 S d_1_inp [7:0] $end
$var wire 8 T d_inp_0 [7:0] $end
$var wire 8 U d_inp_1 [7:0] $end
$var wire 8 V rand_1 [7:0] $end
$var wire 8 W rand_1_inp [7:0] $end
$var wire 8 X rand_2 [7:0] $end
$var wire 8 Y rand_2_inp [7:0] $end
$var wire 8 Z u01_HPC20 [7:0] $end
$var wire 8 [ u01_HPC21 [7:0] $end
$var wire 8 \ u10_HPC20 [7:0] $end
$var wire 8 ] u10_HPC21 [7:0] $end
$var wire 8 ^ x_0 [7:0] $end
$var wire 8 _ x_1 [7:0] $end
$var wire 8 ` y_0 [7:0] $end
$var wire 8 a y_1 [7:0] $end
$var wire 8 b z11_assgn11 [7:0] $end
$var wire 8 c z13_assgn13 [7:0] $end
$var wire 8 d z15_assgn15 [7:0] $end
$var wire 8 e z17_assgn17 [7:0] $end
$var wire 8 f z19_assgn19 [7:0] $end
$var wire 8 g z1_assgn1 [7:0] $end
$var wire 8 h z21_assgn21 [7:0] $end
$var wire 8 i z23_assgn23 [7:0] $end
$var wire 8 j z3_assgn3 [7:0] $end
$var wire 8 k z5_assgn5 [7:0] $end
$var wire 8 l z7_assgn7 [7:0] $end
$var wire 8 m z9_assgn9 [7:0] $end
$var reg 8 n a_inp_0_reg [7:0] $end
$var reg 8 o a_inp_1_reg [7:0] $end
$var reg 8 p a_neg_hpc2_w_1_order0_HPC20_reg [7:0] $end
$var reg 8 q a_neg_hpc2_w_1_order0_HPC21_reg [7:0] $end
$var reg 8 r a_neg_hpc2_w_1_order1_HPC20_reg [7:0] $end
$var reg 8 s a_neg_hpc2_w_1_order1_HPC21_reg [7:0] $end
$var reg 8 t b_share_reg_hpc2_same_shares_1_order0_HPC20 [7:0] $end
$var reg 8 u b_share_reg_hpc2_same_shares_1_order0_HPC21 [7:0] $end
$var reg 8 v b_share_reg_hpc2_same_shares_1_order1_HPC20 [7:0] $end
$var reg 8 w b_share_reg_hpc2_same_shares_1_order1_HPC21 [7:0] $end
$var reg 8 x c_inp_0_reg [7:0] $end
$var reg 8 y c_inp_1_reg [7:0] $end
$var reg 8 z rand_reg_hpc2_w_1_order0_HPC20 [7:0] $end
$var reg 8 { rand_reg_hpc2_w_1_order0_HPC21 [7:0] $end
$var reg 8 | rand_reg_hpc2_w_1_order1_HPC20 [7:0] $end
$var reg 8 } rand_reg_hpc2_w_1_order1_HPC21 [7:0] $end
$var reg 8 ~ temp_hpc2_v_1_order0_HPC20 [7:0] $end
$var reg 8 !" temp_hpc2_v_1_order0_HPC21 [7:0] $end
$var reg 8 "" temp_hpc2_v_1_order1_HPC20 [7:0] $end
$var reg 8 #" temp_hpc2_v_1_order1_HPC21 [7:0] $end
$var reg 8 $" u00_HPC20 [7:0] $end
$var reg 8 %" u00_HPC21 [7:0] $end
$var reg 8 &" u11_HPC20 [7:0] $end
$var reg 8 '" u11_HPC21 [7:0] $end
$var reg 8 (" v01_HPC20 [7:0] $end
$var reg 8 )" v01_HPC21 [7:0] $end
$var reg 8 *" v10_HPC20 [7:0] $end
$var reg 8 +" v10_HPC21 [7:0] $end
$var reg 8 ," w01_HPC20 [7:0] $end
$var reg 8 -" w01_HPC21 [7:0] $end
$var reg 8 ." w10_HPC20 [7:0] $end
$var reg 8 /" w10_HPC21 [7:0] $end
$var reg 8 0" w_0 [7:0] $end
$var reg 8 1" w_1 [7:0] $end
$upscope $end
$upscope $end
$enddefinitions $end
$comment Show the parameter values. $end
$dumpall
$end
#0
$dumpvars
bx 1"
bx 0"
bx /"
bx ."
bx -"
bx ,"
bx +"
bx *"
bx )"
bx ("
bx '"
bx &"
bx %"
bx $"
bx #"
bx ""
bx !"
bx ~
bx }
bx |
bx {
bx z
bx y
bx x
bx w
bx v
bx u
bx t
bx s
bx r
bx q
bx p
bx o
bx n
bx m
bx l
bx k
bx j
bx i
bx h
bx g
bx f
bx e
bx d
bx c
bx b
bx a
bx `
bx _
bx ^
bx ]
bx \
bx [
bx Z
b0 Y
b0 X
b0 W
b0 V
b0 U
b0 T
b0 S
b0 R
b0 Q
b0 P
b0 O
b0 N
b0 M
b0 L
b0 K
b0 J
b0 I
b0 H
b0 G
b0 F
b0 E
b0 D
b11111111 C
b11111111 B
b11111111 A
b11111111 @
b0 ?
b0 >
b0 =
b0 <
b0 ;
b0 :
bx 9
bx 8
bx 7
bx 6
bx 5
bx 4
bx 3
bx 2
bx 1
bx 0
bx /
b0 .
b0 -
bx ,
b0 +
b0 *
0)
b0 (
b0 '
b0 &
b0 %
b0 $
b0 #
bx "
bx !
$end
#5000
b0 h
b0 i
b0 f
b0 e
b0 d
b0 c
b0 m
b0 b
b0 l
b0 k
b0 j
b0 g
b0 w
b11111111 s
b0 }
b0 y
b0 #"
b11111111 q
b0 {
b0 !"
b0 x
b0 u
b0 v
b11111111 r
b0 |
b0 o
b0 ""
b11111111 p
b0 z
b0 ~
b0 n
b0 t
1)
#10000
0)
#15000
b0 `
b0 ^
b0 a
b0 ]
b0 [
b0 _
b0 \
b0 Z
b0 '"
b0 /"
b0 +"
b0 -"
b0 )"
b0 %"
b0 &"
b0 ."
b0 *"
b0 ,"
b0 ("
b0 $"
1)
#20000
0)
#25000
b0 !
b0 1"
b0 "
b0 0"
1)
#30000
0)
#35000
1)
#40000
0)
#45000
1)
#50000
0)
#55000
1)
#60000
0)
#65000
1)
#70000
0)
#75000
1)
#80000
0)
#85000
1)
#90000
0)
#95000
1)
#100000
0)
#105000
1)
#110000
0)
#115000
1)
#120000
0)
#125000
1)
#130000
0)
#135000
1)
#140000
0)
#145000
1)
#150000
0)
#155000
1)
#160000
0)
#165000
1)
#170000
0)
#175000
1)
#180000
0)
#185000
1)
#190000
0)
#195000
1)
#200000
0)
#205000
1)
#210000
0)
#215000
1)
#220000
0)
#225000
1)
#230000
0)
#235000
1)
#240000
0)
#245000
1)
#250000
0)
#255000
1)
#260000
0)
#265000
1)
#270000
0)
#275000
1)
#280000
0)
#285000
1)
#290000
0)
#295000
b111101 C
b111110 A
b10110101 B
b1100000 @
b11000011 6
b11000011 5
b10010 2
b11 1
b11101011 0
b11010101 /
b101101 W
b101101 -
b101101 V
b10010000 Y
b10010000 .
b10010000 X
b11110111 U
b11110111 S
b11110111 +
b11110111 R
b11100101 T
b11100101 Q
b11100101 *
b11100101 P
b11000010 O
b11000010 M
b11000010 (
b11000010 L
b11000001 N
b11000001 K
b11000001 '
b11000001 J
b10110110 I
b10110110 G
b10110110 &
b10110110 F
b1011101 H
b1011101 E
b1011101 %
b1011101 D
b1001010 ?
b1001010 =
b1001010 $
b1001010 <
b10011111 >
b10011111 ;
b10011111 #
b10011111 :
b1 4
b10000 7
b11000010101111100110000001011000110000101011111001100010010110001100010010111110011000000101100011000100101111100110001001011000110001101011111001100000010110001100011010111110011000100101100011001000101111100110000001011000110010001011111001100010010110001110010011000010110111001100100010111110011001000101100011100100110000101101110011001000101111100110001001011000110000100101100011000100010110001100011001011000110010000101100011011110111010101110100001011000110111101110101011101000011001000001010 ,
b10000000000000000000000000000011 3
1)
#300000
0)
#305000
b10000 h
b11000010 i
b1000000 f
b10000 e
b1000001 d
b11000001 c
b100101 m
b10 b
b1000000 l
b100000 k
b10011011 j
b11101 g
b11110111 w
b111101 s
b10010000 }
b11000010 y
b1110101 #"
b111110 q
b10010000 {
b1100111 !"
b11000001 x
b11100101 u
b10110110 v
b10110101 r
b101101 |
b1001010 o
b1110000 ""
b1100000 p
b101101 z
b10011011 ~
b10011111 n
b1011101 t
b0 8
1)
#310000
0)
#315000
b10010010 a
b1010000 ]
b1010001 [
b10010000 `
b1100111 _
b1100101 \
b10111011 Z
b10100110 ^
b11000010 '"
b10000 /"
b1000000 +"
b10000 -"
b1000001 )"
b11000001 %"
b10 &"
b100101 ."
b1000000 *"
b100000 ,"
b10011011 ("
b11101 $"
b1 8
1)
#320000
0)
#325000
b11110101 !
b11110101 1"
b110110 "
b110110 0"
b10 8
1)
#330000
0)
#335000
b11111 C
b1100011 A
b11000010 B
b11010010 @
b111000 6
b111000 5
b10111000 2
b1111100 1
b101010 0
b10000 /
b11011011 W
b11011011 -
b11011011 V
b11101000 Y
b11101000 .
b11101000 X
b101000 U
b101000 S
b101000 +
b101000 R
b10010000 T
b10010000 Q
b10010000 *
b10010000 P
b11100000 O
b11100000 M
b11100000 (
b11100000 L
b10011100 N
b10011100 K
b10011100 '
b10011100 J
b10110001 I
b10110001 G
b10110001 &
b10110001 F
b10011011 H
b10011011 E
b10011011 %
b10011011 D
b111101 ?
b111101 =
b111101 $
b111101 <
b101101 >
b101101 ;
b101101 #
b101101 :
b10 4
b11000011 9
b11 8
1)
#340000
0)
#345000
b1000 h
b100000 i
b1100000 f
b1100000 e
b10000000 d
b10010000 c
b11000010 m
b110001 b
b0 l
b11010010 k
b101000 j
b1001 g
b101000 w
b11111 s
b11101000 }
b11100000 y
b1111000 #"
b1100011 q
b11101000 {
b11000000 !"
b10011100 x
b10010000 u
b10110001 v
b11000010 r
b11011011 |
b111101 o
b1000000 ""
b11010010 p
b11011011 z
b1101010 ~
b101101 n
b10011011 t
b0 8
1)
#350000
0)
#355000
b1001000 a
b1101000 ]
b11100000 [
b1110000 `
b11110011 _
b11000010 \
b11111010 Z
b11110011 ^
b100000 '"
b1000 /"
b1100000 +"
b1100000 -"
b10000000 )"
b10010000 %"
b110001 &"
b11000010 ."
b0 *"
b11010010 ,"
b101000 ("
b1001 $"
b1 8
1)
#360000
0)
#365000
b10111011 !
b10111011 1"
b10000011 "
b10000011 0"
b10 8
1)
#370000
0)
#375000
b10101011 C
b10001011 A
b1010101 B
b100111 @
b10000 6
b10000 5
b110001 2
b100000 1
b110101 0
b1110010 /
b10010100 W
b10010100 -
b10010100 V
b110 Y
b110 .
b110 X
b1110100 U
b1110100 S
b1110100 +
b1110100 R
b1000101 T
b1000101 Q
b1000101 *
b1000101 P
b1010100 O
b1010100 M
b1010100 (
b1010100 L
b1110100 N
b1110100 K
b1110100 '
b1110100 J
b1100000 I
b1100000 G
b1100000 &
b1100000 F
b1010101 H
b1010101 E
b1010101 %
b1010101 D
b10101010 ?
b10101010 =
b10101010 $
b10101010 <
b11011000 >
b11011000 ;
b11011000 #
b11011000 :
b11 4
b111000 9
b11 8
1)
#380000
0)
#385000
b10 h
b1010100 i
b1000000 f
b10 e
b1110000 d
b1000100 c
b10100 m
b100000 b
b10000000 l
b100 k
b11010000 j
b1010000 g
b1110100 w
b10101011 s
b110 }
b1010100 y
b1000011 #"
b10001011 q
b110 {
b1110010 !"
b1110100 x
b1000101 u
b1100000 v
b1010101 r
b10010100 |
b10101010 o
b11000001 ""
b100111 p
b10010100 z
b11110100 ~
b11011000 n
b1010101 t
b0 8
1)
#390000
0)
#395000
b10110 a
b1000010 ]
b1110010 [
b110110 `
b10110100 _
b10010100 \
b11010100 Z
b10000100 ^
b1010100 '"
b10 /"
b1000000 +"
b10 -"
b1110000 )"
b1000100 %"
b100000 &"
b10100 ."
b10000000 *"
b100 ,"
b11010000 ("
b1010000 $"
b1 8
1)
#400000
0)
#405000
b10100010 !
b10100010 1"
b10110010 "
b10110010 0"
b10 8
1)
#410000
0)
#415000
b1101110 C
b10010101 A
b1001100 B
b11100010 @
b1000000 6
b1000000 5
b11101100 2
b11111011 1
b10101001 0
b10101110 /
b10001001 W
b10001001 -
b10001001 V
b11101001 Y
b11101001 .
b11101001 X
b1010000 U
b1010000 S
b1010000 +
b1010000 R
b10111100 T
b10111100 Q
b10111100 *
b10111100 P
b10010001 O
b10010001 M
b10010001 (
b10010001 L
b1101010 N
b1101010 K
b1101010 '
b1101010 J
b11111001 I
b11111001 G
b11111001 &
b11111001 F
b1010000 H
b1010000 E
b1010000 %
b1010000 D
b10110011 ?
b10110011 =
b10110011 $
b10110011 <
b11101 >
b11101 ;
b11101 #
b11101 :
b100 4
b10000 9
b11 8
1)
#420000
0)
#425000
b1101000 h
b10000 i
b10001 f
b10000001 e
b101000 d
b101000 c
b1000 m
b10110001 b
b10010001 l
b10000000 k
b10000 j
b10000 g
b1010000 w
b1101110 s
b11101001 }
b10010001 y
b1010101 #"
b10010101 q
b11101001 {
b10111001 !"
b1101010 x
b10111100 u
b11111001 v
b1001100 r
b10001001 |
b10110011 o
b11011001 ""
b11100010 p
b10001001 z
b1110000 ~
b11101 n
b1010000 t
b0 8
1)
#430000
0)
#435000
b1101001 a
b1111001 ]
b10101001 [
b10000001 `
b101000 _
b10011001 \
b10010000 Z
b10000000 ^
b10000 '"
b1101000 /"
b10001 +"
b10000001 -"
b101000 )"
b101000 %"
b10110001 &"
b1000 ."
b10010001 *"
b10000000 ,"
b10000 ("
b10000 $"
b1 8
1)
#440000
0)
#445000
b1000001 !
b1000001 1"
b1 "
b1 0"
b10 8
1)
#450000
0)
#455000
b111011 C
b10111 A
b1001000 B
b11111 @
b1110111 6
b1110111 5
b100111 2
b101100 1
b11011011 0
b1010111 /
b1101100 W
b1101100 -
b1101100 V
b111001 Y
b111001 .
b111001 X
b1111010 U
b1111010 S
b1111010 +
b1111010 R
b1011101 T
b1011101 Q
b1011101 *
b1011101 P
b11000100 O
b11000100 M
b11000100 (
b11000100 L
b11101000 N
b11101000 K
b11101000 '
b11101000 J
b11111100 I
b11111100 G
b11111100 &
b11111100 F
b100111 H
b100111 E
b100111 %
b100111 D
b10110111 ?
b10110111 =
b10110111 $
b10110111 <
b11100000 >
b11100000 ;
b11100000 #
b11100000 :
b101 4
b1000000 9
b11 8
1)
#460000
0)
#465000
b111001 h
b1000000 i
b1000100 f
b10001 e
b1000000 d
b1001000 c
b1001000 m
b10110100 b
b11 l
b1100 k
b10000000 j
b100000 g
b1111010 w
b111011 s
b111001 }
b11000100 y
b1100100 #"
b10111 q
b111001 {
b1000011 !"
b11101000 x
b1011101 u
b11111100 v
b1001000 r
b1101100 |
b10110111 o
b1001011 ""
b11111 p
b1101100 z
b10010000 ~
b11100000 n
b100111 t
b0 8
1)
#470000
0)
#475000
b111101 a
b1111101 ]
b1010001 [
b11001 `
b11111111 _
b1001011 \
b10001100 Z
b10101100 ^
b1000000 '"
b111001 /"
b1000100 +"
b10001 -"
b1000000 )"
b1001000 %"
b10110100 &"
b1001000 ."
b11 *"
b1100 ,"
b10000000 ("
b100000 $"
b1 8
1)
#480000
0)
#485000
b11000010 !
b11000010 1"
b10110101 "
b10110101 0"
b10 8
1)
#490000
0)
#495000
b10101000 C
b11011001 A
b111011 B
b11101 @
b1100010 6
b1100010 5
b1100110 2
b1110001 1
b100110 /
b11001100 W
b11001100 -
b11001100 V
b100001 Y
b100001 .
b100001 X
b11101010 U
b11101010 S
b11101010 +
b11101010 R
b10001100 T
b10001100 Q
b10001100 *
b10001100 P
b1010111 O
b1010111 M
b1010111 (
b1010111 L
b100110 N
b100110 K
b100110 '
b100110 J
b10111000 I
b10111000 G
b10111000 &
b10111000 F
b1100011 H
b1100011 E
b1100011 %
b1100011 D
b11000100 ?
b11000100 =
b11000100 $
b11000100 <
b11100010 >
b11100010 ;
b11100010 #
b11100010 :
b110 4
b1110111 9
b11 8
1)
#500000
0)
#505000
b100000 h
b1000010 i
b101 f
b1 e
b10 d
b100 c
b1000 m
b10000000 b
b10000100 l
b1100000 j
b1100010 g
b11101010 w
b10101000 s
b100001 }
b1010111 y
b10101101 #"
b11011001 q
b100001 {
b11001011 !"
b100110 x
b10001100 u
b10111000 v
b111011 r
b11001100 |
b11000100 o
b10101111 ""
b11101 p
b11001100 z
b1110100 ~
b11100010 n
b1100011 t
b0 8
1)
#510000
0)
